<?xml version="1.0" encoding="utf-8"?>
<document version="2">
<interlinear-text guid="3e7f6099-5594-4b3e-b916-6a9e63f6bc5d">
    <item type="title" lang="wbl">MSK ruboi 2 </item>
    <item type="source" lang="en">Wakhi songs</item>
    <item type="source" lang="wbl">çikwor bajdiʃ</item>
    <paragraphs>
      <paragraph guid="bb1cca00-e12f-4a01-835f-670fac66f7fd">
        <phrases>
          <phrase guid="bd120a16-046a-4c22-a50f-9bc395b508c1">
            <item type="segnum" lang="en">1</item>
            <words>
              <word guid="6e7766b8-6d83-4643-b951-d2cc1ca460d1">
                <item type="txt" lang="wbl">ej</item>
                <morphemes>
                  <morph type="stem" guid="d7f713e8-e8cf-11d3-9764-00c04f186933">
                    <item type="txt" lang="wbl">əj</item>
                    <item type="cf" lang="wbl">e</item>
                    <item type="gls" lang="en">hey</item>
                    <item type="msa" lang="en">interj</item>
                  </morph>
                </morphemes>
                <item type="gls" lang="en">hey</item>
              </word>
              <word guid="76ecc80d-7837-436d-971d-7917706555ee">
                <item type="txt" lang="wbl">xədo</item>
                <morphemes>
                  <morph type="stem" guid="d7f713e8-e8cf-11d3-9764-00c04f186933">
                    <item type="txt" lang="wbl">xədo</item>
                    <item type="cf" lang="wbl">xədo</item>
                    <item type="gls" lang="en">God</item>
                    <item type="msa" lang="en">n</item>
                  </morph>
                </morphemes>
                <item type="gls" lang="en">god</item>
              </word>
              <word>
                <item type="punct" lang="en">,</item>
              </word>
              <word guid="932987b9-a28a-4385-8c14-712a78f848f6">
                <item type="txt" lang="wbl">çanəm</item>
                <morphemes>
                  <morph type="stem" guid="d7f713e8-e8cf-11d3-9764-00c04f186933">
                    <item type="txt" lang="wbl">çan</item>
                    <item type="cf" lang="wbl">çan</item>
                    <item type="gls" lang="en">say</item>
                    <item type="msa" lang="en">v</item>
                  </morph>
                  <morph type="suffix" guid="d7f713dd-e8cf-11d3-9764-00c04f186933">
                    <item type="txt" lang="wbl">-əm</item>
                    <item type="cf" lang="wbl">-əm</item>
                    <item type="hn" lang="wbl">1</item>
                    <item type="gls" lang="en">-1SG.NPST</item>
                    <item type="msa" lang="en">v:Tns/Agr</item>
                  </morph>
                </morphemes>
                <item type="gls" lang="en"></item>
              </word>
              <word guid="b1746485-b5c1-4012-b7ef-a7d3e35e7c2a">
                <item type="txt" lang="wbl">tu</item>
                <morphemes>
                  <morph type="stem" guid="d7f713e8-e8cf-11d3-9764-00c04f186933">
                    <item type="txt" lang="wbl">tu</item>
                    <item type="cf" lang="wbl">tu</item>
                    <item type="gls" lang="en">2SG.NOM</item>
                    <item type="msa" lang="en">pro</item>
                  </morph>
                </morphemes>
                <item type="gls" lang="en"></item>
              </word>
              <word guid="a35acdc7-b03e-4ba6-b201-fecfc34497eb">
                <item type="txt" lang="wbl">ɣərib</item>
                <morphemes>
                  <morph type="stem" guid="d7f713e8-e8cf-11d3-9764-00c04f186933">
                    <item type="txt" lang="wbl">ɣərib</item>
                    <item type="cf" lang="wbl">ɣərib</item>
                    <item type="gls" lang="en">stranger</item>
                    <item type="msa" lang="en">n</item>
                  </morph>
                </morphemes>
              </word>
              <word guid="b2b50085-d41f-4dbd-a712-5e6db378c4a7">
                <item type="txt" lang="wbl">maʐi</item>
                <morphemes>
                  <morph type="stem" guid="d7f713e8-e8cf-11d3-9764-00c04f186933">
                    <item type="txt" lang="wbl">maʐ</item>
                    <item type="cf" lang="wbl">maʐ</item>
                    <item type="gls" lang="en">1SG.OBL</item>
                    <item type="msa" lang="en">proobl</item>
                  </morph>
                  <morph type="suffix" guid="d7f713dd-e8cf-11d3-9764-00c04f186933">
                    <item type="txt" lang="wbl">-i</item>
                    <item type="cf" lang="wbl">-i</item>
                    <item type="hn" lang="wbl">3</item>
                    <item type="gls" lang="en">-OBL</item>
                    <item type="msa" lang="en">n:(Case1)</item>
                  </morph>
                </morphemes>
              </word>
              <word guid="132be43e-a5a7-4cf3-9f3f-fa7b667e9fc3">
                <item type="txt" lang="wbl">mətsar</item>
                <morphemes>
                  <morph type="prefix" guid="d7f713db-e8cf-11d3-9764-00c04f186933">
                    <item type="txt" lang="wbl">mə-</item>
                    <item type="cf" lang="wbl">mə-</item>
                    <item type="gls" lang="en">NEG.SBJNC-</item>
                    <item type="msa" lang="en">v:(Neg)</item>
                  </morph>
                  <morph type="stem" guid="d7f713e8-e8cf-11d3-9764-00c04f186933">
                    <item type="txt" lang="wbl">tsar</item>
                    <item type="cf" lang="wbl">tsar</item>
                    <item type="gls" lang="en">do</item>
                    <item type="msa" lang="en">LightV</item>
                  </morph>
                  <morph type="suffix" guid="d7f713dd-e8cf-11d3-9764-00c04f186933">
                    <item type="txt" lang="wbl">-∅</item>
                    <item type="cf" lang="wbl">-∅</item>
                    <item type="gls" lang="en">-2SG.NPST</item>
                    <item type="msa" lang="en">v:Tns/Agr</item>
                  </morph>
                </morphemes>
              </word>
              <word>
                <item type="punct" lang="en">,</item>
              </word>
              <word guid="8f67a004-7791-4b26-83d6-8aae778d1cbe">
                <item type="txt" lang="wbl">bimori</item>
              </word>
              <word guid="6592fafc-9697-4081-ad4d-9e6bb0990636">
                <item type="txt" lang="wbl">vərzət</item>
              </word>
              <word guid="2721d9da-ccb5-4dfa-8c88-93f5608d62f9">
                <item type="txt" lang="wbl">bi</item>
                <morphemes>
                  <morph type="prefix" guid="d7f713db-e8cf-11d3-9764-00c04f186933">
                    <item type="txt" lang="wbl">bi-</item>
                    <item type="cf" lang="wbl">bi-</item>
                    <item type="hn" lang="wbl">1</item>
                    <item type="gls" lang="en">without</item>
                    <item type="msa" lang="en">Attaches to any category</item>
                  </morph>
                </morphemes>
              </word>
              <word guid="63102c8b-c2a0-43f1-bcb9-3f7c5cb4c24a">
                <item type="txt" lang="wbl">təbib</item>
                <morphemes>
                  <morph type="stem" guid="d7f713e8-e8cf-11d3-9764-00c04f186933">
                    <item type="txt" lang="wbl">təbib</item>
                    <item type="cf" lang="wbl">tabib</item>
                    <item type="variantTypes" lang="en">+fr. var. of</item>
                    <item type="gls" lang="en">doctor</item>
                    <item type="msa" lang="en">n</item>
                  </morph>
                </morphemes>
                <item type="gls" lang="en">doctor</item>
              </word>
              <word guid="5b282670-0bf0-43b3-a5a2-142030e6913c">
                <item type="txt" lang="wbl">maʐi</item>
                <morphemes>
                  <morph type="stem" guid="d7f713e8-e8cf-11d3-9764-00c04f186933">
                    <item type="txt" lang="wbl">maʐ</item>
                    <item type="cf" lang="wbl">maʐ</item>
                    <item type="gls" lang="en">1SG.OBL</item>
                    <item type="msa" lang="en">proobl</item>
                  </morph>
                  <morph type="suffix" guid="d7f713dd-e8cf-11d3-9764-00c04f186933">
                    <item type="txt" lang="wbl">-i</item>
                    <item type="cf" lang="wbl">-i</item>
                    <item type="hn" lang="wbl">3</item>
                    <item type="gls" lang="en">-OBL</item>
                    <item type="msa" lang="en">n:(Case1)</item>
                  </morph>
                </morphemes>
              </word>
              <word guid="132be43e-a5a7-4cf3-9f3f-fa7b667e9fc3">
                <item type="txt" lang="wbl">mətsar</item>
                <morphemes>
                  <morph type="prefix" guid="d7f713db-e8cf-11d3-9764-00c04f186933">
                    <item type="txt" lang="wbl">mə-</item>
                    <item type="cf" lang="wbl">mə-</item>
                    <item type="gls" lang="en">NEG.SBJNC-</item>
                    <item type="msa" lang="en">v:(Neg)</item>
                  </morph>
                  <morph type="stem" guid="d7f713e8-e8cf-11d3-9764-00c04f186933">
                    <item type="txt" lang="wbl">tsar</item>
                    <item type="cf" lang="wbl">tsar</item>
                    <item type="gls" lang="en">do</item>
                    <item type="msa" lang="en">LightV</item>
                  </morph>
                  <morph type="suffix" guid="d7f713dd-e8cf-11d3-9764-00c04f186933">
                    <item type="txt" lang="wbl">-∅</item>
                    <item type="cf" lang="wbl">-∅</item>
                    <item type="gls" lang="en">-2SG.NPST</item>
                    <item type="msa" lang="en">v:Tns/Agr</item>
                  </morph>
                </morphemes>
              </word>
              <word>
                <item type="punct" lang="en">.</item>
              </word>
            </words>
            <item type="gls" lang="en">Oh God I ask you not to make me a stranger [in a foreign land], don't let me be sick for long and without a doctor. </item>
          </phrase>
        </phrases>
      </paragraph>
      <paragraph guid="0d098ad2-3336-4ea4-adb8-e87bd0961f2c">
        <phrases>
          <phrase guid="5cfd7512-bccd-445c-be90-656c2fbd1da2">
            <item type="segnum" lang="en">2</item>
            <words>
              <word guid="8f67a004-7791-4b26-83d6-8aae778d1cbe">
                <item type="txt" lang="wbl">bimori</item>
              </word>
              <word guid="6592fafc-9697-4081-ad4d-9e6bb0990636">
                <item type="txt" lang="wbl">vərzət</item>
              </word>
              <word guid="8583ac05-68ec-478e-8d41-1c8f0a139f20">
                <item type="txt" lang="wbl">bi</item>
                <morphemes>
                  <morph type="prefix" guid="d7f713db-e8cf-11d3-9764-00c04f186933">
                    <item type="txt" lang="wbl">bi-</item>
                    <item type="cf" lang="wbl">bi-</item>
                    <item type="hn" lang="wbl">1</item>
                    <item type="gls" lang="en">without</item>
                    <item type="msa" lang="en">Attaches to any category</item>
                  </morph>
                </morphemes>
              </word>
              <word guid="63102c8b-c2a0-43f1-bcb9-3f7c5cb4c24a">
                <item type="txt" lang="wbl">təbib</item>
                <morphemes>
                  <morph type="stem" guid="d7f713e8-e8cf-11d3-9764-00c04f186933">
                    <item type="txt" lang="wbl">təbib</item>
                    <item type="cf" lang="wbl">tabib</item>
                    <item type="variantTypes" lang="en">+fr. var. of</item>
                    <item type="gls" lang="en">doctor</item>
                    <item type="msa" lang="en">n</item>
                  </morph>
                </morphemes>
                <item type="gls" lang="en">doctor</item>
              </word>
              <word guid="cb573dd2-8dff-4e62-9ef9-26eb5c2ebd64">
                <item type="txt" lang="wbl">xosti</item>
              </word>
              <word guid="0dfd4439-335f-4849-8f31-a8b34ef39854">
                <item type="txt" lang="wbl">xədoj</item>
                <morphemes>
                  <morph type="stem" guid="d7f713e8-e8cf-11d3-9764-00c04f186933">
                    <item type="txt" lang="wbl">xədo</item>
                    <item type="cf" lang="wbl">xədo</item>
                    <item type="gls" lang="en">God</item>
                    <item type="msa" lang="en">n</item>
                  </morph>
                  <morph type="enclitic" guid="d7f713e1-e8cf-11d3-9764-00c04f186933">
                    <item type="txt" lang="wbl">=i</item>
                    <item type="cf" lang="wbl">=i</item>
                    <item type="gls" lang="en">==3SG</item>
                    <item type="msa" lang="en">TAM</item>
                  </morph>
                </morphemes>
              </word>
              <word>
                <item type="punct" lang="en">,</item>
              </word>
              <word guid="4ae4f358-9e92-4a8d-bfe1-47b1646f28e7">
                <item type="txt" lang="wbl">tsə</item>
                <morphemes>
                  <morph type="root" guid="d7f713e5-e8cf-11d3-9764-00c04f186933">
                    <item type="txt" lang="wbl">tsə</item>
                    <item type="cf" lang="wbl">tsə</item>
                    <item type="hn" lang="wbl">2</item>
                    <item type="gls" lang="en">from</item>
                    <item type="msa" lang="en">Loc/Dir</item>
                  </morph>
                </morphemes>
                <item type="gls" lang="en"></item>
              </word>
              <word guid="c5c43ada-69ce-425d-9265-e9cbc576d78f">
                <item type="txt" lang="wbl">dʒoni</item>
                <morphemes>
                  <morph type="stem" guid="d7f713e8-e8cf-11d3-9764-00c04f186933">
                    <item type="txt" lang="wbl">dʒon</item>
                    <item type="cf" lang="wbl">dʒon</item>
                    <item type="hn" lang="wbl">1</item>
                    <item type="gls" lang="en">jān</item>
                    <item type="msa" lang="en">n</item>
                  </morph>
                  <morph type="suffix" guid="d7f713dd-e8cf-11d3-9764-00c04f186933">
                    <item type="txt" lang="wbl">-i</item>
                    <item type="cf" lang="wbl">-i</item>
                    <item type="hn" lang="wbl">3</item>
                    <item type="gls" lang="en">-OBL</item>
                    <item type="msa" lang="en">n:(Case1)</item>
                  </morph>
                </morphemes>
              </word>
              <word guid="73f38398-9488-44e0-9d14-f364a16280d2">
                <item type="txt" lang="wbl">dʒəwonən</item>
              </word>
              <word guid="b7dd351c-15eb-454d-bab6-b80397b30a86">
                <item type="txt" lang="wbl">binəsib</item>
              </word>
              <word guid="5b282670-0bf0-43b3-a5a2-142030e6913c">
                <item type="txt" lang="wbl">maʐi</item>
                <morphemes>
                  <morph type="stem" guid="d7f713e8-e8cf-11d3-9764-00c04f186933">
                    <item type="txt" lang="wbl">maʐ</item>
                    <item type="cf" lang="wbl">maʐ</item>
                    <item type="gls" lang="en">1SG.OBL</item>
                    <item type="msa" lang="en">proobl</item>
                  </morph>
                  <morph type="suffix" guid="d7f713dd-e8cf-11d3-9764-00c04f186933">
                    <item type="txt" lang="wbl">-i</item>
                    <item type="cf" lang="wbl">-i</item>
                    <item type="hn" lang="wbl">3</item>
                    <item type="gls" lang="en">-OBL</item>
                    <item type="msa" lang="en">n:(Case1)</item>
                  </morph>
                </morphemes>
              </word>
              <word guid="9ddffe64-c608-4aba-9219-e41a2f29b72c">
                <item type="txt" lang="wbl">mətsar</item>
                <morphemes>
                  <morph type="prefix" guid="d7f713db-e8cf-11d3-9764-00c04f186933">
                    <item type="txt" lang="wbl">mə-</item>
                    <item type="cf" lang="wbl">mə-</item>
                    <item type="gls" lang="en">NEG.SBJNC-</item>
                    <item type="msa" lang="en">v:(Neg)</item>
                  </morph>
                  <morph type="stem" guid="d7f713e8-e8cf-11d3-9764-00c04f186933">
                    <item type="txt" lang="wbl">tsar</item>
                    <item type="cf" lang="wbl">tsar</item>
                    <item type="gls" lang="en">do</item>
                    <item type="msa" lang="en">LightV</item>
                  </morph>
                  <morph type="suffix" guid="d7f713dd-e8cf-11d3-9764-00c04f186933">
                    <item type="txt" lang="wbl">-∅</item>
                    <item type="cf" lang="wbl">-∅</item>
                    <item type="gls" lang="en">-2SG.NPST</item>
                    <item type="msa" lang="en">v:Tns/Agr</item>
                  </morph>
                </morphemes>
              </word>
              <word>
                <item type="punct" lang="en">.</item>
              </word>
            </words>
            <item type="gls" lang="en">Being sick for a long time without a doctor is up to God, [so I ask] please don't separate me from my dear youth.</item>
          </phrase>
        </phrases>
      </paragraph>
      <paragraph guid="12dbc9bd-3fe6-4cd5-8618-1f3da8ef3a28">
        <phrases>
          <phrase guid="3f1c0796-9556-48c2-bd54-2237ffc0bbe4">
            <item type="segnum" lang="en">3</item>
            <words>
              <word guid="d0d76d6e-86b7-4f1b-a2c3-e2caae1c8b51">
                <item type="txt" lang="wbl">nandʒoni</item>
              </word>
              <word guid="b6eeb093-fc38-4191-894d-3c21cd79b67e">
                <item type="txt" lang="wbl">ʂirin</item>
              </word>
              <word guid="57aa717e-05d8-40d3-b5e6-f10a5d17be3f">
                <item type="txt" lang="wbl">ti</item>
                <morphemes>
                  <morph type="stem" guid="d7f713e8-e8cf-11d3-9764-00c04f186933">
                    <item type="txt" lang="wbl">ti</item>
                    <item type="cf" lang="wbl">ti</item>
                    <item type="gls" lang="en">2SG.GEN</item>
                    <item type="msa" lang="en">poss</item>
                  </morph>
                </morphemes>
                <item type="gls" lang="en">your</item>
              </word>
              <word guid="4c96dea9-a63e-4e87-8f94-707e25be49f7">
                <item type="txt" lang="wbl">didorər</item>
              </word>
              <word guid="cffbb4e0-1a27-4b50-93da-ef8926f04f11">
                <item type="txt" lang="wbl">zor</item>
                <morphemes>
                  <morph type="stem" guid="d7f713e8-e8cf-11d3-9764-00c04f186933">
                    <item type="txt" lang="wbl">sor</item>
                    <item type="cf" lang="wbl">sor</item>
                    <item type="gls" lang="en">grain</item>
                    <item type="msa" lang="en">n</item>
                  </morph>
                </morphemes>
                <item type="gls" lang="en">grain</item>
              </word>
              <word guid="a2651d51-4780-48fd-97a8-5a3965659c0b">
                <item type="txt" lang="wbl">vitəm</item>
                <morphemes>
                  <morph type="stem" guid="d7f713e8-e8cf-11d3-9764-00c04f186933">
                    <item type="txt" lang="wbl">vi</item>
                    <item type="cf" lang="wbl">wots</item>
                    <item type="gls" lang="en">become</item>
                    <item type="msa" lang="en">v</item>
                  </morph>
                  <morph type="suffix" guid="d7f713dd-e8cf-11d3-9764-00c04f186933">
                    <item type="txt" lang="wbl">-t</item>
                    <item type="cf" lang="wbl">-t</item>
                    <item type="hn" lang="wbl">2</item>
                    <item type="gls" lang="en">-PST</item>
                    <item type="msa" lang="en">v:Pst1</item>
                  </morph>
                  <morph type="enclitic" guid="d7f713e1-e8cf-11d3-9764-00c04f186933">
                    <item type="txt" lang="wbl">=əm</item>
                    <item type="cf" lang="wbl">=əm</item>
                    <item type="gls" lang="en">==1SG</item>
                    <item type="msa" lang="en">TAM</item>
                  </morph>
                </morphemes>
              </word>
              <word>
                <item type="punct" lang="en">,</item>
              </word>
              <word guid="d10a5c4f-6382-466f-b923-cc60d763189f">
                <item type="txt" lang="wbl">tsə</item>
                <morphemes>
                  <morph type="root" guid="d7f713e5-e8cf-11d3-9764-00c04f186933">
                    <item type="txt" lang="wbl">tsə</item>
                    <item type="cf" lang="wbl">tsə</item>
                    <item type="hn" lang="wbl">2</item>
                    <item type="gls" lang="en">from</item>
                    <item type="msa" lang="en">Loc/Dir</item>
                  </morph>
                </morphemes>
                <item type="gls" lang="en"></item>
              </word>
              <word guid="c143714c-33d3-4940-a057-c58754ad4e78">
                <item type="txt" lang="wbl">nowinaki</item>
              </word>
              <word guid="57aa717e-05d8-40d3-b5e6-f10a5d17be3f">
                <item type="txt" lang="wbl">ti</item>
                <morphemes>
                  <morph type="stem" guid="d7f713e8-e8cf-11d3-9764-00c04f186933">
                    <item type="txt" lang="wbl">ti</item>
                    <item type="cf" lang="wbl">ti</item>
                    <item type="gls" lang="en">2SG.GEN</item>
                    <item type="msa" lang="en">poss</item>
                  </morph>
                </morphemes>
                <item type="gls" lang="en">your</item>
              </word>
              <word guid="3a9c788d-e1ca-4859-be64-2e473a37d92f">
                <item type="txt" lang="wbl">rujən</item>
                <morphemes>
                  <morph type="stem" guid="d7f713e8-e8cf-11d3-9764-00c04f186933">
                    <item type="txt" lang="wbl">ruj</item>
                    <item type="cf" lang="wbl">ruj</item>
                    <item type="gls" lang="en">face</item>
                    <item type="msa" lang="en">n</item>
                  </morph>
                  <morph type="suffix" guid="d7f713dd-e8cf-11d3-9764-00c04f186933">
                    <item type="txt" lang="wbl">-ən</item>
                    <item type="cf" lang="wbl">-n</item>
                    <item type="gls" lang="en">-ABL</item>
                    <item type="msa" lang="en">n:(Case2)</item>
                  </morph>
                </morphemes>
              </word>
              <word guid="78fb241f-3e5e-457a-bd32-d401f00cee71">
                <item type="txt" lang="wbl">bimor</item>
                <morphemes>
                  <morph type="stem" guid="d7f713e8-e8cf-11d3-9764-00c04f186933">
                    <item type="txt" lang="wbl">bimor</item>
                    <item type="cf" lang="wbl">bemor</item>
                    <item type="variantTypes" lang="en">+fr. var. of</item>
                    <item type="gls" lang="en">sick</item>
                    <item type="msa" lang="en">adj</item>
                  </morph>
                </morphemes>
                <item type="gls" lang="en">sick</item>
              </word>
              <word guid="d0737e30-3e2c-43cd-a3ad-e30268d5613f">
                <item type="txt" lang="wbl">vitəm</item>
                <morphemes>
                  <morph type="stem" guid="d7f713e8-e8cf-11d3-9764-00c04f186933">
                    <item type="txt" lang="wbl">vi</item>
                    <item type="cf" lang="wbl">wots</item>
                    <item type="gls" lang="en">become</item>
                    <item type="msa" lang="en">v</item>
                  </morph>
                  <morph type="suffix" guid="d7f713dd-e8cf-11d3-9764-00c04f186933">
                    <item type="txt" lang="wbl">-t</item>
                    <item type="cf" lang="wbl">-t</item>
                    <item type="hn" lang="wbl">2</item>
                    <item type="gls" lang="en">-PST</item>
                    <item type="msa" lang="en">v:Pst1</item>
                  </morph>
                  <morph type="enclitic" guid="d7f713e1-e8cf-11d3-9764-00c04f186933">
                    <item type="txt" lang="wbl">=əm</item>
                    <item type="cf" lang="wbl">=əm</item>
                    <item type="gls" lang="en">==1SG</item>
                    <item type="msa" lang="en">TAM</item>
                  </morph>
                </morphemes>
              </word>
              <word>
                <item type="punct" lang="en">.</item>
              </word>
            </words>
            <item type="gls" lang="en">My dear mother I miss seeing you, from not seeing your face, I became sick.</item>
          </phrase>
        </phrases>
      </paragraph>
      <paragraph guid="145ae6aa-2139-4f56-92f6-bc2bf1dc3257">
        <phrases>
          <phrase guid="2ec0acb3-4135-4ff1-8ebb-8d4012e146c7">
            <item type="segnum" lang="en">4</item>
            <words>
              <word guid="55ec1a4b-6db7-4857-b675-23d8db645245">
                <item type="txt" lang="wbl">wuz</item>
                <morphemes>
                  <morph type="stem" guid="d7f713e8-e8cf-11d3-9764-00c04f186933">
                    <item type="txt" lang="wbl">wuz</item>
                    <item type="cf" lang="wbl">wuz</item>
                    <item type="gls" lang="en">1SG.NOM</item>
                    <item type="msa" lang="en">pronom</item>
                  </morph>
                </morphemes>
                <item type="gls" lang="en">1SG.NOM</item>
              </word>
              <word guid="502a37e0-81c2-471d-b328-3198c6c563b2">
                <item type="txt" lang="wbl">ʃɨkrati</item>
              </word>
              <word guid="fe69d9af-fcab-44cb-b03b-85ecf758d664">
                <item type="txt" lang="wbl">taw</item>
                <morphemes>
                  <morph type="stem" guid="d7f713e8-e8cf-11d3-9764-00c04f186933">
                    <item type="txt" lang="wbl">taw</item>
                    <item type="cf" lang="wbl">taw</item>
                    <item type="gls" lang="en">2SG.OBL</item>
                    <item type="msa" lang="en">pro-form</item>
                  </morph>
                </morphemes>
              </word>
              <word guid="43a94156-c695-4a68-89a6-1aee19279ee4">
                <item type="txt" lang="wbl">nəkərtəm</item>
              </word>
              <word guid="3d5ced15-2174-4302-a86a-7ac0878c3306">
                <item type="txt" lang="wbl">ada</item>
                <morphemes>
                  <morph type="prefix" guid="d7f713db-e8cf-11d3-9764-00c04f186933">
                    <item type="txt" lang="wbl">a-</item>
                    <item type="cf" lang="wbl">a-</item>
                    <item type="gls" lang="en">EMPH-</item>
                    <item type="msa" lang="en">det&gt;det</item>
                  </morph>
                  <morph type="stem" guid="d7f713e8-e8cf-11d3-9764-00c04f186933">
                    <item type="txt" lang="wbl">də</item>
                    <item type="cf" lang="wbl">də</item>
                    <item type="gls" lang="en">LOC</item>
                    <item type="msa" lang="en">Loc/Dir</item>
                  </morph>
                  <morph type="suffix" guid="d7f713dd-e8cf-11d3-9764-00c04f186933">
                    <item type="txt" lang="wbl">-a</item>
                    <item type="cf" lang="wbl">-a</item>
                    <item type="hn" lang="wbl">2</item>
                    <item type="gls" lang="en">-MED</item>
                    <item type="msa" lang="en">det&gt;det</item>
                  </morph>
                </morphemes>
                <item type="gls" lang="en">with it</item>
              </word>
              <word guid="823c63b2-ef5e-435f-9a79-ce7aa98f30bf">
                <item type="txt" lang="wbl">waxtvi</item>
              </word>
              <word>
                <item type="punct" lang="en">,</item>
              </word>
              <word guid="5dc803a6-f09e-471a-ac6f-40fdb65e77fa">
                <item type="txt" lang="wbl">oxir</item>
                <morphemes>
                  <morph type="stem" guid="d7f713e8-e8cf-11d3-9764-00c04f186933">
                    <item type="txt" lang="wbl">oxir</item>
                    <item type="cf" lang="wbl">oxir</item>
                    <item type="gls" lang="en">end</item>
                    <item type="msa" lang="en">n</item>
                  </morph>
                </morphemes>
                <item type="gls" lang="en">end</item>
              </word>
              <word guid="068b9d26-96ae-4452-8509-347116ada052">
                <item type="txt" lang="wbl">çɨ</item>
                <morphemes>
                  <morph type="proclitic" guid="d7f713e2-e8cf-11d3-9764-00c04f186933">
                    <item type="txt" lang="wbl">çɨ=</item>
                    <item type="cf" lang="wbl">çɨ=</item>
                    <item type="gls" lang="en">REFL.POSS=</item>
                    <item type="msa" lang="en">poss</item>
                  </morph>
                </morphemes>
                <item type="gls" lang="en">his</item>
              </word>
              <word guid="2b2fdc94-f8f5-41d2-b4d3-5f0f44e4fb71">
                <item type="txt" lang="wbl">dʒəzorər</item>
              </word>
              <word guid="612c5e46-a8da-46e0-b035-c793773d2898">
                <item type="txt" lang="wbl">giriftorəm</item>
              </word>
              <word guid="d0737e30-3e2c-43cd-a3ad-e30268d5613f">
                <item type="txt" lang="wbl">vitəm</item>
                <morphemes>
                  <morph type="stem" guid="d7f713e8-e8cf-11d3-9764-00c04f186933">
                    <item type="txt" lang="wbl">vi</item>
                    <item type="cf" lang="wbl">wots</item>
                    <item type="gls" lang="en">become</item>
                    <item type="msa" lang="en">v</item>
                  </morph>
                  <morph type="suffix" guid="d7f713dd-e8cf-11d3-9764-00c04f186933">
                    <item type="txt" lang="wbl">-t</item>
                    <item type="cf" lang="wbl">-t</item>
                    <item type="hn" lang="wbl">2</item>
                    <item type="gls" lang="en">-PST</item>
                    <item type="msa" lang="en">v:Pst1</item>
                  </morph>
                  <morph type="enclitic" guid="d7f713e1-e8cf-11d3-9764-00c04f186933">
                    <item type="txt" lang="wbl">=əm</item>
                    <item type="cf" lang="wbl">=əm</item>
                    <item type="gls" lang="en">==1SG</item>
                    <item type="msa" lang="en">TAM</item>
                  </morph>
                </morphemes>
              </word>
              <word>
                <item type="punct" lang="en">.</item>
              </word>
            </words>
            <item type="gls" lang="en">I wasn't grateful to you then, [but] in the end I faced my hardships. </item>
          </phrase>
        </phrases>
      </paragraph>
      <paragraph guid="9a80b677-d61e-4a46-96ed-b0a6ed40f216">
        <phrases>
          <phrase guid="79237aee-0c4b-4157-b73d-4f2e28123e0e">
            <item type="segnum" lang="en">5</item>
            <words>
              <word guid="746bb9e5-2f64-4100-85de-137085678dd9">
                <item type="txt" lang="wbl">sak</item>
                <morphemes>
                  <morph type="stem" guid="d7f713e8-e8cf-11d3-9764-00c04f186933">
                    <item type="txt" lang="wbl">sak</item>
                    <item type="cf" lang="wbl">sak</item>
                    <item type="gls" lang="en">1PL.NOM</item>
                    <item type="msa" lang="en">pronom</item>
                  </morph>
                </morphemes>
                <item type="gls" lang="en">1PL</item>
              </word>
              <word guid="05a78788-4b4b-4d92-b861-5c44ed1e2c7e">
                <item type="txt" lang="wbl">tʂkərənət</item>
              </word>
              <word guid="c6c4dc0c-85aa-4b1f-9b60-cac8015937ce">
                <item type="txt" lang="wbl">spo</item>
                <morphemes>
                  <morph type="stem" guid="d7f713e8-e8cf-11d3-9764-00c04f186933">
                    <item type="txt" lang="wbl">spo</item>
                    <item type="cf" lang="wbl">spo</item>
                    <item type="gls" lang="en">1PL.GEN</item>
                    <item type="msa" lang="en">poss</item>
                  </morph>
                </morphemes>
                <item type="gls" lang="en">our</item>
              </word>
              <word guid="e4326d2d-ee59-4530-8d43-6b5d0051f865">
                <item type="txt" lang="wbl">itʃa</item>
              </word>
              <word guid="8fbca7c3-94de-4eac-a9a6-0f3dff17fa55">
                <item type="txt" lang="wbl">kuət</item>
                <morphemes>
                  <morph type="stem" guid="d7f713e8-e8cf-11d3-9764-00c04f186933">
                    <item type="txt" lang="wbl">ku</item>
                    <item type="cf" lang="wbl">ku</item>
                    <item type="hn" lang="wbl">1</item>
                    <item type="gls" lang="en">mountain</item>
                    <item type="msa" lang="en">n</item>
                  </morph>
                  <morph type="enclitic" guid="d7f713e1-e8cf-11d3-9764-00c04f186933">
                    <item type="txt" lang="wbl">=ət</item>
                    <item type="cf" lang="wbl">=ət</item>
                    <item type="hn" lang="wbl">1</item>
                    <item type="gls" lang="en">=and</item>
                    <item type="msa" lang="en">conn</item>
                  </morph>
                </morphemes>
              </word>
              <word guid="5ee924c5-7520-4766-9687-52754c56ca31">
                <item type="txt" lang="wbl">kəmar</item>
                <morphemes>
                  <morph type="stem" guid="d7f713e8-e8cf-11d3-9764-00c04f186933">
                    <item type="txt" lang="wbl">kəmar</item>
                    <item type="cf" lang="wbl">kəmar</item>
                    <item type="gls" lang="en">belt</item>
                    <item type="msa" lang="en">n</item>
                  </morph>
                </morphemes>
                <item type="gls" lang="en">belt</item>
              </word>
              <word>
                <item type="punct" lang="en">,</item>
              </word>
              <word guid="55ec1a4b-6db7-4857-b675-23d8db645245">
                <item type="txt" lang="wbl">wuz</item>
                <morphemes>
                  <morph type="stem" guid="d7f713e8-e8cf-11d3-9764-00c04f186933">
                    <item type="txt" lang="wbl">wuz</item>
                    <item type="cf" lang="wbl">wuz</item>
                    <item type="gls" lang="en">1SG.NOM</item>
                    <item type="msa" lang="en">pronom</item>
                  </morph>
                </morphemes>
                <item type="gls" lang="en">1SG.NOM</item>
              </word>
              <word guid="99f762d8-aa47-4527-b6d8-38d661df53d8">
                <item type="txt" lang="wbl">bimorəmət</item>
              </word>
              <word guid="0fac7471-9888-4043-b438-73762e2daa97">
                <item type="txt" lang="wbl">ʐɨ</item>
                <morphemes>
                  <morph type="stem" guid="d7f713e8-e8cf-11d3-9764-00c04f186933">
                    <item type="txt" lang="wbl">ʐɨ</item>
                    <item type="cf" lang="wbl">ʐɨ</item>
                    <item type="gls" lang="en">1SG.GEN</item>
                    <item type="msa" lang="en">poss</item>
                  </morph>
                </morphemes>
                <item type="gls" lang="en">my</item>
              </word>
              <word guid="35fe1e1c-2ec2-4857-add0-7368eb56bde5">
                <item type="txt" lang="wbl">nandʒon</item>
                <morphemes>
                  <morph type="stem" guid="d7f713e8-e8cf-11d3-9764-00c04f186933">
                    <item type="txt" lang="wbl">nan</item>
                    <item type="cf" lang="wbl">nan</item>
                    <item type="gls" lang="en">mother</item>
                    <item type="msa" lang="en">n</item>
                  </morph>
                  <morph type="stem" guid="d7f713e8-e8cf-11d3-9764-00c04f186933">
                    <item type="txt" lang="wbl">dʒon</item>
                    <item type="cf" lang="wbl">dʒon</item>
                    <item type="hn" lang="wbl">1</item>
                    <item type="gls" lang="en">jān</item>
                    <item type="msa" lang="en">n</item>
                  </morph>
                </morphemes>
                <item type="gls" lang="en">mother</item>
              </word>
              <word guid="02e9690f-159d-4494-a1de-a5b9c44e2d15">
                <item type="txt" lang="wbl">çatər</item>
                <morphemes>
                  <morph type="stem" guid="d7f713e8-e8cf-11d3-9764-00c04f186933">
                    <item type="txt" lang="wbl">çat</item>
                    <item type="cf" lang="wbl">çat</item>
                    <item type="gls" lang="en">REFL</item>
                    <item type="msa" lang="en">pro</item>
                  </morph>
                  <morph type="suffix" guid="d7f713dd-e8cf-11d3-9764-00c04f186933">
                    <item type="txt" lang="wbl">-r</item>
                    <item type="cf" lang="wbl">-r</item>
                    <item type="gls" lang="en">-DAT</item>
                    <item type="msa" lang="en">n:(Case2)</item>
                  </morph>
                </morphemes>
              </word>
              <word guid="f2d91943-318e-485d-ab2c-88465442c15b">
                <item type="txt" lang="wbl">bixbar</item>
                <morphemes>
                  <morph type="prefix" guid="d7f713db-e8cf-11d3-9764-00c04f186933">
                    <item type="txt" lang="wbl">bi-</item>
                    <item type="cf" lang="wbl">bi-</item>
                    <item type="hn" lang="wbl">1</item>
                    <item type="gls" lang="en">without</item>
                    <item type="msa" lang="en">Attaches to any category</item>
                  </morph>
                  <morph type="stem" guid="d7f713e8-e8cf-11d3-9764-00c04f186933">
                    <item type="txt" lang="wbl">xəbar</item>
                    <item type="cf" lang="wbl">xabar</item>
                    <item type="variantTypes" lang="en">+unspec. var. of</item>
                    <item type="gls" lang="en">news</item>
                    <item type="msa" lang="en">n</item>
                  </morph>
                </morphemes>
                <item type="gls" lang="en">news</item>
              </word>
              <word>
                <item type="punct" lang="en">.</item>
              </word>
            </words>
            <item type="gls" lang="en">We are partridges and our nest is a mountain, I am sick and my dear mother is unaware of it.</item>
          </phrase>
        </phrases>
      </paragraph>
      <paragraph guid="40d8a760-6eb1-48d4-b567-c96a616a837d">
        <phrases>
          <phrase guid="418b3cad-29e0-4aff-9068-f36573616104">
            <item type="segnum" lang="en">6</item>
            <words>
              <word guid="8b3dbd2f-b21e-4f08-896c-61c55f966dd2">
                <item type="txt" lang="wbl">e</item>
                <morphemes>
                  <morph type="stem" guid="d7f713e8-e8cf-11d3-9764-00c04f186933">
                    <item type="txt" lang="wbl">əj</item>
                    <item type="cf" lang="wbl">e</item>
                    <item type="gls" lang="en">hey</item>
                    <item type="msa" lang="en">interj</item>
                  </morph>
                </morphemes>
                <item type="gls" lang="en"></item>
              </word>
              <word guid="248a9222-634a-4cef-890a-89ecbc55d631">
                <item type="txt" lang="wbl">nandʒon</item>
                <morphemes>
                  <morph type="stem" guid="d7f713e8-e8cf-11d3-9764-00c04f186933">
                    <item type="txt" lang="wbl">nan</item>
                    <item type="cf" lang="wbl">nan</item>
                    <item type="gls" lang="en">mother</item>
                    <item type="msa" lang="en">n</item>
                  </morph>
                  <morph type="stem" guid="d7f713e8-e8cf-11d3-9764-00c04f186933">
                    <item type="txt" lang="wbl">dʒon</item>
                    <item type="cf" lang="wbl">dʒon</item>
                    <item type="hn" lang="wbl">1</item>
                    <item type="gls" lang="en">jān</item>
                    <item type="msa" lang="en">n</item>
                  </morph>
                </morphemes>
                <item type="gls" lang="en">mother</item>
              </word>
              <word>
                <item type="punct" lang="en">,</item>
              </word>
              <word guid="068b9d26-96ae-4452-8509-347116ada052">
                <item type="txt" lang="wbl">çɨ</item>
                <morphemes>
                  <morph type="proclitic" guid="d7f713e2-e8cf-11d3-9764-00c04f186933">
                    <item type="txt" lang="wbl">çɨ=</item>
                    <item type="cf" lang="wbl">çɨ=</item>
                    <item type="gls" lang="en">REFL.POSS=</item>
                    <item type="msa" lang="en">poss</item>
                  </morph>
                </morphemes>
                <item type="gls" lang="en">his</item>
              </word>
              <word guid="65b8dd26-8926-418f-89a6-25dac2392344">
                <item type="txt" lang="wbl">pirani</item>
                <morphemes>
                  <morph type="stem" guid="d7f713e8-e8cf-11d3-9764-00c04f186933">
                    <item type="txt" lang="wbl">piran</item>
                    <item type="cf" lang="wbl">piran</item>
                    <item type="gls" lang="en">dress</item>
                    <item type="msa" lang="en">n</item>
                  </morph>
                  <morph type="suffix" guid="d7f713dd-e8cf-11d3-9764-00c04f186933">
                    <item type="txt" lang="wbl">-i</item>
                    <item type="cf" lang="wbl">-i</item>
                    <item type="hn" lang="wbl">3</item>
                    <item type="gls" lang="en">-OBL</item>
                    <item type="msa" lang="en">n:(Case1)</item>
                  </morph>
                </morphemes>
              </word>
              <word guid="353cb45a-1c0b-46af-9d50-68442804a15c">
                <item type="txt" lang="wbl">ɣami</item>
                <morphemes>
                  <morph type="stem" guid="d7f713e8-e8cf-11d3-9764-00c04f186933">
                    <item type="txt" lang="wbl">ɣami</item>
                    <item type="cf" lang="wbl">ɣami</item>
                    <item type="gls" lang="en">dispirited</item>
                    <item type="msa" lang="en">adj</item>
                  </morph>
                </morphemes>
                <item type="gls" lang="en">dispirited</item>
              </word>
              <word guid="6ec7f473-3e3f-4428-8493-827bd6ade6c6">
                <item type="txt" lang="wbl">tu</item>
                <morphemes>
                  <morph type="stem" guid="d7f713e8-e8cf-11d3-9764-00c04f186933">
                    <item type="txt" lang="wbl">tu</item>
                    <item type="cf" lang="wbl">tu</item>
                    <item type="gls" lang="en">2SG.NOM</item>
                    <item type="msa" lang="en">pro</item>
                  </morph>
                </morphemes>
                <item type="gls" lang="en">you</item>
              </word>
              <word guid="7e26fdbc-64c1-4c11-a430-b26e6c843be6">
                <item type="txt" lang="wbl">tʃuʈ</item>
                <morphemes>
                  <morph type="stem" guid="d7f713e8-e8cf-11d3-9764-00c04f186933">
                    <item type="txt" lang="wbl">tʃuʈ</item>
                    <item type="cf" lang="wbl">tʂuʈ</item>
                    <item type="gls" lang="en">tear</item>
                    <item type="msa" lang="en">n</item>
                  </morph>
                </morphemes>
                <item type="gls" lang="en">divide</item>
              </word>
              <word guid="2c54c3ee-87df-487b-b78c-739c9d2daed7">
                <item type="txt" lang="wbl">tsar</item>
                <morphemes>
                  <morph type="stem" guid="d7f713e8-e8cf-11d3-9764-00c04f186933">
                    <item type="txt" lang="wbl">tsar</item>
                    <item type="cf" lang="wbl">tsar</item>
                    <item type="gls" lang="en">do</item>
                    <item type="msa" lang="en">LightV</item>
                  </morph>
                  <morph type="suffix" guid="d7f713dd-e8cf-11d3-9764-00c04f186933">
                    <item type="txt" lang="wbl">-∅</item>
                    <item type="cf" lang="wbl">-∅</item>
                    <item type="gls" lang="en">-2SG.NPST</item>
                    <item type="msa" lang="en">v:Tns/Agr</item>
                  </morph>
                </morphemes>
              </word>
              <word>
                <item type="punct" lang="en">,</item>
              </word>
              <word guid="14ee6860-38dd-4bac-a5f6-50ff2bad4cd1">
                <item type="txt" lang="wbl">naʝd</item>
                <morphemes>
                  <morph type="stem" guid="d7f713e8-e8cf-11d3-9764-00c04f186933">
                    <item type="txt" lang="wbl">naʝd</item>
                    <item type="cf" lang="wbl">naʝd</item>
                    <item type="gls" lang="en">night</item>
                    <item type="msa" lang="en">n</item>
                  </morph>
                </morphemes>
                <item type="gls" lang="en">night</item>
              </word>
              <word guid="063547bf-ce3a-4472-8871-a6d4e0eccd26">
                <item type="txt" lang="wbl">tə</item>
                <morphemes>
                  <morph type="stem" guid="d7f713e8-e8cf-11d3-9764-00c04f186933">
                    <item type="txt" lang="wbl">tə</item>
                    <item type="cf" lang="wbl">tə</item>
                    <item type="gls" lang="en">DAT</item>
                    <item type="msa" lang="en">Loc/Dir</item>
                  </morph>
                </morphemes>
                <item type="gls" lang="en">DAT</item>
              </word>
              <word guid="068b9d26-96ae-4452-8509-347116ada052">
                <item type="txt" lang="wbl">çɨ</item>
                <morphemes>
                  <morph type="proclitic" guid="d7f713e2-e8cf-11d3-9764-00c04f186933">
                    <item type="txt" lang="wbl">çɨ=</item>
                    <item type="cf" lang="wbl">çɨ=</item>
                    <item type="gls" lang="en">REFL.POSS=</item>
                    <item type="msa" lang="en">poss</item>
                  </morph>
                </morphemes>
                <item type="gls" lang="en">his</item>
              </word>
              <word guid="b16bee85-9702-430a-91e6-f76c9535ce59">
                <item type="txt" lang="wbl">vorz</item>
                <morphemes>
                  <morph type="stem" guid="d7f713e8-e8cf-11d3-9764-00c04f186933">
                    <item type="txt" lang="wbl">vorz</item>
                    <item type="cf" lang="wbl">vorz</item>
                    <item type="gls" lang="en">pillow</item>
                    <item type="msa" lang="en">n</item>
                  </morph>
                </morphemes>
                <item type="gls" lang="en">pillow</item>
              </word>
              <word guid="da1b88ee-dc75-4919-b0fc-bffcaf9e450b">
                <item type="txt" lang="wbl">diət</item>
                <morphemes>
                  <morph type="stem" guid="d7f713e8-e8cf-11d3-9764-00c04f186933">
                    <item type="txt" lang="wbl">di</item>
                    <item type="cf" lang="wbl">di</item>
                    <item type="gls" lang="en">hit</item>
                    <item type="msa" lang="en">v</item>
                  </morph>
                  <morph type="suffix" guid="d7f713dd-e8cf-11d3-9764-00c04f186933">
                    <item type="txt" lang="wbl">-∅</item>
                    <item type="cf" lang="wbl">-∅</item>
                    <item type="gls" lang="en">-2SG.NPST</item>
                    <item type="msa" lang="en">v:Tns/Agr</item>
                  </morph>
                  <morph type="enclitic" guid="d7f713e1-e8cf-11d3-9764-00c04f186933">
                    <item type="txt" lang="wbl">=ət</item>
                    <item type="cf" lang="wbl">=ət</item>
                    <item type="hn" lang="wbl">1</item>
                    <item type="gls" lang="en">=and</item>
                    <item type="msa" lang="en">conn</item>
                  </morph>
                </morphemes>
              </word>
              <word guid="1c67f263-3ee7-4308-ad0c-82e6ba81bc92">
                <item type="txt" lang="wbl">rwor</item>
                <morphemes>
                  <morph type="stem" guid="d7f713e8-e8cf-11d3-9764-00c04f186933">
                    <item type="txt" lang="wbl">rwor</item>
                    <item type="cf" lang="wbl">rwor</item>
                    <item type="gls" lang="en">day</item>
                    <item type="msa" lang="en">n</item>
                  </morph>
                </morphemes>
              </word>
              <word guid="a74d78c8-7677-4d3d-971f-5ddf207c7cc3">
                <item type="txt" lang="wbl">bət</item>
                <morphemes>
                  <morph>
                    <item type="txt" lang="wbl">bət</item>
                  </morph>
                </morphemes>
                <item type="gls" lang="en">no.more</item>
              </word>
              <word guid="c28fd270-53f2-4d77-8714-d3a40b9c3ad8">
                <item type="txt" lang="wbl">nola</item>
                <morphemes>
                  <morph type="stem" guid="d7f713e8-e8cf-11d3-9764-00c04f186933">
                    <item type="txt" lang="wbl">nola</item>
                    <item type="cf" lang="wbl">nola</item>
                    <item type="gls" lang="en">wailing</item>
                    <item type="msa" lang="en">n</item>
                  </morph>
                </morphemes>
                <item type="gls" lang="en">wailing</item>
              </word>
              <word guid="9ddffe64-c608-4aba-9219-e41a2f29b72c">
                <item type="txt" lang="wbl">mətsar</item>
                <morphemes>
                  <morph type="prefix" guid="d7f713db-e8cf-11d3-9764-00c04f186933">
                    <item type="txt" lang="wbl">mə-</item>
                    <item type="cf" lang="wbl">mə-</item>
                    <item type="gls" lang="en">NEG.SBJNC-</item>
                    <item type="msa" lang="en">v:(Neg)</item>
                  </morph>
                  <morph type="stem" guid="d7f713e8-e8cf-11d3-9764-00c04f186933">
                    <item type="txt" lang="wbl">tsar</item>
                    <item type="cf" lang="wbl">tsar</item>
                    <item type="gls" lang="en">do</item>
                    <item type="msa" lang="en">LightV</item>
                  </morph>
                  <morph type="suffix" guid="d7f713dd-e8cf-11d3-9764-00c04f186933">
                    <item type="txt" lang="wbl">-∅</item>
                    <item type="cf" lang="wbl">-∅</item>
                    <item type="gls" lang="en">-2SG.NPST</item>
                    <item type="msa" lang="en">v:Tns/Agr</item>
                  </morph>
                </morphemes>
              </word>
              <word>
                <item type="punct" lang="en">.</item>
              </word>
            </words>
            <item type="gls" lang="en">Oh dear mother, you should tear your greiving [lit. unhappy] dress, put it under your pillow at night and in the day don't wail.</item>
          </phrase>
        </phrases>
      </paragraph>
      <paragraph guid="d87af07d-95bf-4b03-bd2b-9b0490b3e31d">
        <phrases>
          <phrase guid="d5e30db1-658e-4aa5-b7e4-9aacfcb13299">
            <item type="segnum" lang="en">7</item>
            <words>
              <word guid="4f4f326b-6b14-4357-a47c-0af190faa7a9">
                <item type="txt" lang="wbl">nəməki</item>
              </word>
              <word guid="0c56fd0b-4a08-42c7-87e3-d4f9a94c42f0">
                <item type="txt" lang="wbl">ʂuri</item>
              </word>
              <word guid="79e079e0-53e4-4836-bca9-9e2fba3e92cb">
                <item type="txt" lang="wbl">ar</item>
                <morphemes>
                  <morph type="prefix" guid="d7f713db-e8cf-11d3-9764-00c04f186933">
                    <item type="txt" lang="wbl">a-</item>
                    <item type="cf" lang="wbl">a-</item>
                    <item type="gls" lang="en">EMPH-</item>
                    <item type="msa" lang="en">det&gt;det</item>
                  </morph>
                  <morph type="stem" guid="d7f713e8-e8cf-11d3-9764-00c04f186933">
                    <item type="txt" lang="wbl">ər</item>
                    <item type="cf" lang="wbl">rə</item>
                    <item type="variantTypes" lang="en">+fr. var. of</item>
                    <item type="gls" lang="en">ALL</item>
                    <item type="msa" lang="en">Loc/Dir</item>
                  </morph>
                </morphemes>
                <item type="gls" lang="en"></item>
              </word>
              <word guid="30e38855-c895-4303-9451-00625870cc89">
                <item type="txt" lang="wbl">zaxmii</item>
              </word>
              <word guid="46483794-26e4-4b29-bcf6-a2541afe9893">
                <item type="txt" lang="wbl">toza</item>
                <morphemes>
                  <morph type="stem" guid="d7f713e8-e8cf-11d3-9764-00c04f186933">
                    <item type="txt" lang="wbl">toza</item>
                    <item type="cf" lang="wbl">toza</item>
                    <item type="gls" lang="en">clean</item>
                    <item type="msa" lang="en">adj</item>
                  </morph>
                </morphemes>
                <item type="gls" lang="en">new</item>
              </word>
              <word guid="85cd846a-db95-4ea8-bc88-b9ef1cd3bd29">
                <item type="txt" lang="wbl">məkaʈ</item>
                <morphemes>
                  <morph type="prefix" guid="d7f713db-e8cf-11d3-9764-00c04f186933">
                    <item type="txt" lang="wbl">mə-</item>
                    <item type="cf" lang="wbl">mə-</item>
                    <item type="gls" lang="en">NEG.SBJNC-</item>
                    <item type="msa" lang="en">v:(Neg)</item>
                  </morph>
                  <morph type="stem" guid="d7f713e8-e8cf-11d3-9764-00c04f186933">
                    <item type="txt" lang="wbl">kaʈ</item>
                    <item type="cf" lang="wbl">kaʈ</item>
                    <item type="gls" lang="en">put</item>
                    <item type="msa" lang="en">v</item>
                  </morph>
                  <morph type="suffix" guid="d7f713dd-e8cf-11d3-9764-00c04f186933">
                    <item type="txt" lang="wbl">-∅</item>
                    <item type="cf" lang="wbl">-∅</item>
                    <item type="gls" lang="en">-2SG.NPST</item>
                  </morph>
                </morphemes>
              </word>
              <word>
                <item type="punct" lang="en">,</item>
              </word>
              <word guid="5b282670-0bf0-43b3-a5a2-142030e6913c">
                <item type="txt" lang="wbl">maʐi</item>
                <morphemes>
                  <morph type="stem" guid="d7f713e8-e8cf-11d3-9764-00c04f186933">
                    <item type="txt" lang="wbl">maʐ</item>
                    <item type="cf" lang="wbl">maʐ</item>
                    <item type="gls" lang="en">1SG.OBL</item>
                    <item type="msa" lang="en">proobl</item>
                  </morph>
                  <morph type="suffix" guid="d7f713dd-e8cf-11d3-9764-00c04f186933">
                    <item type="txt" lang="wbl">-i</item>
                    <item type="cf" lang="wbl">-i</item>
                    <item type="hn" lang="wbl">3</item>
                    <item type="gls" lang="en">-OBL</item>
                    <item type="msa" lang="en">n:(Case1)</item>
                  </morph>
                </morphemes>
              </word>
              <word guid="28459fdf-39f5-46e6-8e53-be567fb3f84c">
                <item type="txt" lang="wbl">ʃitət</item>
                <morphemes>
                  <morph type="stem" guid="d7f713e8-e8cf-11d3-9764-00c04f186933">
                    <item type="txt" lang="wbl">ʃi</item>
                    <item type="cf" lang="wbl">ʃaj</item>
                    <item type="gls" lang="en">kill</item>
                    <item type="msa" lang="en">v</item>
                  </morph>
                  <morph type="suffix" guid="d7f713dd-e8cf-11d3-9764-00c04f186933">
                    <item type="txt" lang="wbl">-t</item>
                    <item type="cf" lang="wbl">-t</item>
                    <item type="hn" lang="wbl">2</item>
                    <item type="gls" lang="en">-PST</item>
                    <item type="msa" lang="en">v:Pst1</item>
                  </morph>
                  <morph type="enclitic" guid="d7f713e1-e8cf-11d3-9764-00c04f186933">
                    <item type="txt" lang="wbl">=ət</item>
                    <item type="cf" lang="wbl">=ət</item>
                    <item type="hn" lang="wbl">2</item>
                    <item type="gls" lang="en">==2SG</item>
                    <item type="msa" lang="en">TAM</item>
                  </morph>
                </morphemes>
              </word>
              <word guid="6ec7f473-3e3f-4428-8493-827bd6ade6c6">
                <item type="txt" lang="wbl">tu</item>
                <morphemes>
                  <morph type="stem" guid="d7f713e8-e8cf-11d3-9764-00c04f186933">
                    <item type="txt" lang="wbl">tu</item>
                    <item type="cf" lang="wbl">tu</item>
                    <item type="gls" lang="en">2SG.NOM</item>
                    <item type="msa" lang="en">pro</item>
                  </morph>
                </morphemes>
                <item type="gls" lang="en">you</item>
              </word>
              <word guid="a74d78c8-7677-4d3d-971f-5ddf207c7cc3">
                <item type="txt" lang="wbl">bət</item>
                <morphemes>
                  <morph>
                    <item type="txt" lang="wbl">bət</item>
                  </morph>
                </morphemes>
                <item type="gls" lang="en">no.more</item>
              </word>
              <word guid="c76deec4-6494-4c76-bf1d-5c7e962e8ddf">
                <item type="txt" lang="wbl">owoza</item>
                <morphemes>
                  <morph type="stem" guid="d7f713e8-e8cf-11d3-9764-00c04f186933">
                    <item type="txt" lang="wbl">owoza</item>
                    <item type="cf" lang="wbl">owoza</item>
                    <item type="gls" lang="en">rumor</item>
                    <item type="msa" lang="en">n</item>
                  </morph>
                </morphemes>
                <item type="gls" lang="en">rumor</item>
              </word>
              <word guid="85cd846a-db95-4ea8-bc88-b9ef1cd3bd29">
                <item type="txt" lang="wbl">məkaʈ</item>
                <morphemes>
                  <morph type="prefix" guid="d7f713db-e8cf-11d3-9764-00c04f186933">
                    <item type="txt" lang="wbl">mə-</item>
                    <item type="cf" lang="wbl">mə-</item>
                    <item type="gls" lang="en">NEG.SBJNC-</item>
                    <item type="msa" lang="en">v:(Neg)</item>
                  </morph>
                  <morph type="stem" guid="d7f713e8-e8cf-11d3-9764-00c04f186933">
                    <item type="txt" lang="wbl">kaʈ</item>
                    <item type="cf" lang="wbl">kaʈ</item>
                    <item type="gls" lang="en">put</item>
                    <item type="msa" lang="en">v</item>
                  </morph>
                  <morph type="suffix" guid="d7f713dd-e8cf-11d3-9764-00c04f186933">
                    <item type="txt" lang="wbl">-∅</item>
                    <item type="cf" lang="wbl">-∅</item>
                    <item type="gls" lang="en">-2SG.NPST</item>
                  </morph>
                </morphemes>
              </word>
              <word>
                <item type="punct" lang="en">.</item>
              </word>
            </words>
            <item type="gls" lang="en">Don't put pure salt on a clean new cut, it kills me, and don't spread rumors. </item>
          </phrase>
        </phrases>
      </paragraph>
      <paragraph guid="25210841-c9fa-43d0-b08c-6c7d241978f5">
        <phrases>
          <phrase guid="72509545-d421-4750-b4ec-5d01555128f4">
            <item type="segnum" lang="en">8</item>
            <words>
              <word guid="5b282670-0bf0-43b3-a5a2-142030e6913c">
                <item type="txt" lang="wbl">maʐi</item>
                <morphemes>
                  <morph type="stem" guid="d7f713e8-e8cf-11d3-9764-00c04f186933">
                    <item type="txt" lang="wbl">maʐ</item>
                    <item type="cf" lang="wbl">maʐ</item>
                    <item type="gls" lang="en">1SG.OBL</item>
                    <item type="msa" lang="en">proobl</item>
                  </morph>
                  <morph type="suffix" guid="d7f713dd-e8cf-11d3-9764-00c04f186933">
                    <item type="txt" lang="wbl">-i</item>
                    <item type="cf" lang="wbl">-i</item>
                    <item type="hn" lang="wbl">3</item>
                    <item type="gls" lang="en">-OBL</item>
                    <item type="msa" lang="en">n:(Case1)</item>
                  </morph>
                </morphemes>
              </word>
              <word guid="28459fdf-39f5-46e6-8e53-be567fb3f84c">
                <item type="txt" lang="wbl">ʃitət</item>
                <morphemes>
                  <morph type="stem" guid="d7f713e8-e8cf-11d3-9764-00c04f186933">
                    <item type="txt" lang="wbl">ʃi</item>
                    <item type="cf" lang="wbl">ʃaj</item>
                    <item type="gls" lang="en">kill</item>
                    <item type="msa" lang="en">v</item>
                  </morph>
                  <morph type="suffix" guid="d7f713dd-e8cf-11d3-9764-00c04f186933">
                    <item type="txt" lang="wbl">-t</item>
                    <item type="cf" lang="wbl">-t</item>
                    <item type="hn" lang="wbl">2</item>
                    <item type="gls" lang="en">-PST</item>
                    <item type="msa" lang="en">v:Pst1</item>
                  </morph>
                  <morph type="enclitic" guid="d7f713e1-e8cf-11d3-9764-00c04f186933">
                    <item type="txt" lang="wbl">=ət</item>
                    <item type="cf" lang="wbl">=ət</item>
                    <item type="hn" lang="wbl">2</item>
                    <item type="gls" lang="en">==2SG</item>
                    <item type="msa" lang="en">TAM</item>
                  </morph>
                </morphemes>
              </word>
              <word guid="d4422cd4-b0de-4fc1-86be-ed747c760854">
                <item type="txt" lang="wbl">də</item>
                <morphemes>
                  <morph type="stem" guid="d7f713e8-e8cf-11d3-9764-00c04f186933">
                    <item type="txt" lang="wbl">də</item>
                    <item type="cf" lang="wbl">də</item>
                    <item type="gls" lang="en">LOC</item>
                    <item type="msa" lang="en">Loc/Dir</item>
                  </morph>
                </morphemes>
                <item type="gls" lang="en">in</item>
              </word>
              <word guid="068b9d26-96ae-4452-8509-347116ada052">
                <item type="txt" lang="wbl">çɨ</item>
                <morphemes>
                  <morph type="proclitic" guid="d7f713e2-e8cf-11d3-9764-00c04f186933">
                    <item type="txt" lang="wbl">çɨ=</item>
                    <item type="cf" lang="wbl">çɨ=</item>
                    <item type="gls" lang="en">REFL.POSS=</item>
                    <item type="msa" lang="en">poss</item>
                  </morph>
                </morphemes>
                <item type="gls" lang="en">his</item>
              </word>
              <word guid="86640592-8c38-404c-8061-534f9146869a">
                <item type="txt" lang="wbl">dastən</item>
                <morphemes>
                  <morph type="stem" guid="d7f713e8-e8cf-11d3-9764-00c04f186933">
                    <item type="txt" lang="wbl">dast</item>
                    <item type="cf" lang="wbl">dast</item>
                    <item type="gls" lang="en">hand</item>
                    <item type="msa" lang="en">n</item>
                  </morph>
                  <morph type="suffix" guid="d7f713dd-e8cf-11d3-9764-00c04f186933">
                    <item type="txt" lang="wbl">-ən</item>
                    <item type="cf" lang="wbl">-n</item>
                    <item type="gls" lang="en">-ABL</item>
                    <item type="msa" lang="en">n:(Case2)</item>
                  </morph>
                </morphemes>
              </word>
              <word guid="de0c4086-867c-4a79-b38e-b872eedc261e">
                <item type="txt" lang="wbl">kəfan</item>
                <morphemes>
                  <morph>
                    <item type="txt" lang="wbl">kəfan</item>
                  </morph>
                </morphemes>
                <item type="gls" lang="en">shroud</item>
              </word>
              <word guid="b9b275bc-cf90-496e-88b6-c668aaed8b56">
                <item type="txt" lang="wbl">goçtət</item>
                <morphemes>
                  <morph type="stem" guid="d7f713e8-e8cf-11d3-9764-00c04f186933">
                    <item type="txt" lang="wbl">goç</item>
                    <item type="cf" lang="wbl">goç</item>
                    <item type="gls" lang="en">make</item>
                    <item type="msa" lang="en">v</item>
                  </morph>
                  <morph type="suffix" guid="d7f713dd-e8cf-11d3-9764-00c04f186933">
                    <item type="txt" lang="wbl">-t</item>
                    <item type="cf" lang="wbl">-t</item>
                    <item type="hn" lang="wbl">1</item>
                    <item type="gls" lang="en">-3SG.NPST</item>
                    <item type="msa" lang="en">v:Tns/Agr</item>
                  </morph>
                  <morph type="enclitic" guid="d7f713e1-e8cf-11d3-9764-00c04f186933">
                    <item type="txt" lang="wbl">=ət</item>
                    <item type="cf" lang="wbl">=ət</item>
                    <item type="hn" lang="wbl">1</item>
                    <item type="gls" lang="en">=and</item>
                    <item type="msa" lang="en">conn</item>
                  </morph>
                </morphemes>
              </word>
              <word>
                <item type="punct" lang="en">,</item>
              </word>
              <word guid="6c2902b1-098c-41eb-aab0-801f2d55c2c8">
                <item type="txt" lang="wbl">niv</item>
                <morphemes>
                  <morph type="stem" guid="d7f713e8-e8cf-11d3-9764-00c04f186933">
                    <item type="txt" lang="wbl">niv</item>
                    <item type="cf" lang="wbl">niv</item>
                    <item type="gls" lang="en">now</item>
                    <item type="msa" lang="en">adv</item>
                  </morph>
                </morphemes>
                <item type="gls" lang="en">now</item>
              </word>
              <word guid="a48fa256-1782-4ab9-83c3-9f6140bd7d31">
                <item type="txt" lang="wbl">maʐ</item>
                <morphemes>
                  <morph type="stem" guid="d7f713e8-e8cf-11d3-9764-00c04f186933">
                    <item type="txt" lang="wbl">maʐ</item>
                    <item type="cf" lang="wbl">maʐ</item>
                    <item type="gls" lang="en">1SG.OBL</item>
                    <item type="msa" lang="en">proobl</item>
                  </morph>
                </morphemes>
                <item type="gls" lang="en">1SG</item>
              </word>
              <word guid="a9b9c9dc-e738-4dbf-b494-e996e28aa684">
                <item type="txt" lang="wbl">bɨt</item>
              </word>
              <word guid="4502adfe-95ff-42b4-bb5f-dcee5caa6ba1">
                <item type="txt" lang="wbl">bə</item>
                <morphemes>
                  <morph type="enclitic" guid="d7f713e1-e8cf-11d3-9764-00c04f186933">
                    <item type="txt" lang="wbl">=bə</item>
                    <item type="cf" lang="wbl">=bə</item>
                    <item type="gls" lang="en">=also</item>
                    <item type="msa" lang="en">adv</item>
                  </morph>
                </morphemes>
                <item type="gls" lang="en">also</item>
              </word>
              <word guid="86b72cf7-3e78-46b8-bc25-3d21877fd344">
                <item type="txt" lang="wbl">dasti</item>
                <morphemes>
                  <morph type="stem" guid="d7f713e8-e8cf-11d3-9764-00c04f186933">
                    <item type="txt" lang="wbl">dast</item>
                    <item type="cf" lang="wbl">dast</item>
                    <item type="gls" lang="en">hand</item>
                    <item type="msa" lang="en">n</item>
                  </morph>
                  <morph type="suffix" guid="d7f713dd-e8cf-11d3-9764-00c04f186933">
                    <item type="txt" lang="wbl">-i</item>
                    <item type="cf" lang="wbl">-i</item>
                    <item type="hn" lang="wbl">3</item>
                    <item type="gls" lang="en">-OBL</item>
                    <item type="msa" lang="en">n:(Case1)</item>
                  </morph>
                </morphemes>
                <item type="gls" lang="en">hand</item>
              </word>
              <word guid="183adc6f-a633-4c59-9a9e-a0749210e1e9">
                <item type="txt" lang="wbl">ətʃ</item>
                <morphemes>
                  <morph type="stem" guid="d7f713e8-e8cf-11d3-9764-00c04f186933">
                    <item type="txt" lang="wbl">ətʃ</item>
                    <item type="cf" lang="wbl">itʃ</item>
                    <item type="variantTypes" lang="en">+dial. var. of</item>
                    <item type="gls" lang="en">none</item>
                    <item type="msa" lang="en">quant</item>
                  </morph>
                </morphemes>
                <item type="gls" lang="en">any</item>
              </word>
              <word guid="17cd3386-be8d-4763-8e41-d020aa3ccac4">
                <item type="txt" lang="wbl">bigona</item>
                <morphemes>
                  <morph type="prefix" guid="d7f713db-e8cf-11d3-9764-00c04f186933">
                    <item type="txt" lang="wbl">bi-</item>
                    <item type="cf" lang="wbl">bi-</item>
                    <item type="hn" lang="wbl">1</item>
                    <item type="gls" lang="en">without</item>
                    <item type="msa" lang="en">Attaches to any category</item>
                  </morph>
                  <morph type="stem" guid="d7f713e8-e8cf-11d3-9764-00c04f186933">
                    <item type="txt" lang="wbl">gona</item>
                    <item type="cf" lang="wbl">gunoh*</item>
                    <item type="variantTypes" lang="en">+fr. var. of</item>
                    <item type="gls" lang="en">sin</item>
                    <item type="msa" lang="en">n</item>
                  </morph>
                </morphemes>
              </word>
              <word guid="85cd846a-db95-4ea8-bc88-b9ef1cd3bd29">
                <item type="txt" lang="wbl">məkaʈ</item>
                <morphemes>
                  <morph type="prefix" guid="d7f713db-e8cf-11d3-9764-00c04f186933">
                    <item type="txt" lang="wbl">mə-</item>
                    <item type="cf" lang="wbl">mə-</item>
                    <item type="gls" lang="en">NEG.SBJNC-</item>
                    <item type="msa" lang="en">v:(Neg)</item>
                  </morph>
                  <morph type="stem" guid="d7f713e8-e8cf-11d3-9764-00c04f186933">
                    <item type="txt" lang="wbl">kaʈ</item>
                    <item type="cf" lang="wbl">kaʈ</item>
                    <item type="gls" lang="en">put</item>
                    <item type="msa" lang="en">v</item>
                  </morph>
                  <morph type="suffix" guid="d7f713dd-e8cf-11d3-9764-00c04f186933">
                    <item type="txt" lang="wbl">-∅</item>
                    <item type="cf" lang="wbl">-∅</item>
                    <item type="gls" lang="en">-2SG.NPST</item>
                  </morph>
                </morphemes>
              </word>
              <word>
                <item type="punct" lang="en">.</item>
              </word>
            </words>
            <item type="gls" lang="en">When it kills me, sew me a kafan [cloth] with your hand, never let me be in a stranger's hand again.</item>
          </phrase>
        </phrases>
      </paragraph>
      <paragraph guid="74264211-9b52-4ab9-8791-42581f33e863">
        <phrases>
          <phrase guid="35516b38-0582-4c52-a173-3f5ad5df2bec">
            <item type="segnum" lang="en">9</item>
            <words>
              <word guid="179ed09e-754f-40e4-bf76-55c8d265be9d">
                <item type="txt" lang="wbl">e</item>
                <morphemes>
                  <morph type="stem" guid="d7f713e8-e8cf-11d3-9764-00c04f186933">
                    <item type="txt" lang="wbl">əj</item>
                    <item type="cf" lang="wbl">e</item>
                    <item type="gls" lang="en">hey</item>
                    <item type="msa" lang="en">interj</item>
                  </morph>
                </morphemes>
                <item type="gls" lang="en"></item>
              </word>
              <word guid="d0d76d6e-86b7-4f1b-a2c3-e2caae1c8b51">
                <item type="txt" lang="wbl">nandʒoni</item>
              </word>
              <word guid="08907b1f-5f00-4f45-bea6-23a0b0ef5e57">
                <item type="txt" lang="wbl">dʒon</item>
                <morphemes>
                  <morph type="stem" guid="d7f713e8-e8cf-11d3-9764-00c04f186933">
                    <item type="txt" lang="wbl">dʒon</item>
                    <item type="cf" lang="wbl">dʒon</item>
                    <item type="hn" lang="wbl">1</item>
                    <item type="gls" lang="en">jān</item>
                    <item type="msa" lang="en">n</item>
                  </morph>
                </morphemes>
                <item type="gls" lang="en">soul</item>
              </word>
              <word>
                <item type="punct" lang="en">,</item>
              </word>
              <word guid="6ec7f473-3e3f-4428-8493-827bd6ade6c6">
                <item type="txt" lang="wbl">tu</item>
                <morphemes>
                  <morph type="stem" guid="d7f713e8-e8cf-11d3-9764-00c04f186933">
                    <item type="txt" lang="wbl">tu</item>
                    <item type="cf" lang="wbl">tu</item>
                    <item type="gls" lang="en">2SG.NOM</item>
                    <item type="msa" lang="en">pro</item>
                  </morph>
                </morphemes>
                <item type="gls" lang="en">you</item>
              </word>
              <word guid="dadaa1dd-c2c1-4e3a-b05f-596166bf1d70">
                <item type="txt" lang="wbl">biwəfoi</item>
              </word>
              <word guid="24151167-c77e-4a85-b753-dd14194306c5">
                <item type="txt" lang="wbl">mətsarə</item>
              </word>
              <word>
                <item type="punct" lang="en">,</item>
              </word>
              <word guid="8954256d-7bf1-40ef-ba00-4335ef891f9a">
                <item type="txt" lang="wbl">dəm</item>
                <morphemes>
                  <morph type="stem" guid="d7f713e8-e8cf-11d3-9764-00c04f186933">
                    <item type="txt" lang="wbl">də</item>
                    <item type="cf" lang="wbl">də</item>
                    <item type="gls" lang="en">LOC</item>
                    <item type="msa" lang="en">Loc/Dir</item>
                  </morph>
                  <morph type="suffix" guid="d7f713dd-e8cf-11d3-9764-00c04f186933">
                    <item type="txt" lang="wbl">-m</item>
                    <item type="cf" lang="wbl">-m</item>
                    <item type="gls" lang="en">-PROX</item>
                    <item type="msa" lang="en">det:(Proximity)</item>
                  </morph>
                </morphemes>
              </word>
              <word guid="9c6aec33-35e4-4f12-bb6a-6abd56076823">
                <item type="txt" lang="wbl">çnaki</item>
              </word>
              <word guid="ec7fc893-b446-4ef1-a229-765d9ea25b71">
                <item type="txt" lang="wbl">dəʂmanvən</item>
              </word>
              <word guid="2598de17-fd06-49c0-a088-98c84738d1a5">
                <item type="txt" lang="wbl">xətoi</item>
              </word>
              <word guid="a586ee26-9cca-4525-a790-3b423894eefc">
                <item type="txt" lang="wbl">mətsare</item>
              </word>
              <word>
                <item type="punct" lang="en">.</item>
              </word>
            </words>
            <item type="gls" lang="en">Oh dear mother, don't be unfaithful, don't make the mistake of believing the things [your] enemies say. </item>
          </phrase>
        </phrases>
      </paragraph>
      <paragraph guid="c7385cae-57b0-4286-bde5-aae1d6a61fff">
        <phrases>
          <phrase guid="dc540705-e06b-482c-9714-e65401516b1d">
            <item type="segnum" lang="en">10</item>
            <words>
              <word guid="939b2642-4cdc-4924-818c-18e6df426378">
                <item type="txt" lang="wbl">dəʂmaniʃ</item>
              </word>
              <word>
                <item type="punct" lang="en">,</item>
              </word>
              <word guid="35891dee-5631-45b6-b142-f3d9712b8bb0">
                <item type="txt" lang="wbl">agar</item>
                <morphemes>
                  <morph type="stem" guid="d7f713e8-e8cf-11d3-9764-00c04f186933">
                    <item type="txt" lang="wbl">agar</item>
                    <item type="cf" lang="wbl">agar</item>
                    <item type="gls" lang="en">if</item>
                    <item type="msa" lang="en">comp</item>
                  </morph>
                </morphemes>
                <item type="gls" lang="en">if</item>
              </word>
              <word guid="068b9d26-96ae-4452-8509-347116ada052">
                <item type="txt" lang="wbl">çɨ</item>
                <morphemes>
                  <morph type="proclitic" guid="d7f713e2-e8cf-11d3-9764-00c04f186933">
                    <item type="txt" lang="wbl">çɨ=</item>
                    <item type="cf" lang="wbl">çɨ=</item>
                    <item type="gls" lang="en">REFL.POSS=</item>
                    <item type="msa" lang="en">poss</item>
                  </morph>
                </morphemes>
                <item type="gls" lang="en">his</item>
              </word>
              <word guid="ef3bcf0b-8f72-4409-9802-a6fb708af05c">
                <item type="txt" lang="wbl">simət</item>
              </word>
              <word guid="b01852e2-4414-474c-8cc9-9fde49c02178">
                <item type="txt" lang="wbl">zar</item>
                <morphemes>
                  <morph type="stem" guid="d7f713e8-e8cf-11d3-9764-00c04f186933">
                    <item type="txt" lang="wbl">zar</item>
                    <item type="cf" lang="wbl">zar</item>
                    <item type="hn" lang="wbl">3</item>
                    <item type="gls" lang="en">weak, poison </item>
                    <item type="msa" lang="en">&lt;Not Sure&gt;</item>
                  </morph>
                </morphemes>
                <item type="gls" lang="en">weak, poison </item>
              </word>
              <word guid="8579c532-11ad-4224-96a9-32bbfbb9728c">
                <item type="txt" lang="wbl">tar</item>
                <morphemes>
                  <morph type="stem" guid="d7f713e8-e8cf-11d3-9764-00c04f186933">
                    <item type="txt" lang="wbl">ta</item>
                    <item type="cf" lang="wbl">taw</item>
                    <item type="gls" lang="en">2SG.OBL</item>
                    <item type="msa" lang="en">pro-form</item>
                  </morph>
                  <morph type="suffix" guid="d7f713dd-e8cf-11d3-9764-00c04f186933">
                    <item type="txt" lang="wbl">-r</item>
                    <item type="cf" lang="wbl">-r</item>
                    <item type="gls" lang="en">-DAT</item>
                    <item type="msa" lang="en">n:(Case2)</item>
                  </morph>
                </morphemes>
                <item type="gls" lang="en"></item>
              </word>
              <word guid="d10a5c4f-6382-466f-b923-cc60d763189f">
                <item type="txt" lang="wbl">tsə</item>
                <morphemes>
                  <morph type="root" guid="d7f713e5-e8cf-11d3-9764-00c04f186933">
                    <item type="txt" lang="wbl">tsə</item>
                    <item type="cf" lang="wbl">tsə</item>
                    <item type="hn" lang="wbl">2</item>
                    <item type="gls" lang="en">from</item>
                    <item type="msa" lang="en">Loc/Dir</item>
                  </morph>
                </morphemes>
                <item type="gls" lang="en"></item>
              </word>
              <word guid="21d265d6-d5b0-44d4-bb2e-aaa1728e19c8">
                <item type="txt" lang="wbl">randən</item>
                <morphemes>
                  <morph type="stem" guid="d7f713e8-e8cf-11d3-9764-00c04f186933">
                    <item type="txt" lang="wbl">rand</item>
                    <item type="cf" lang="wbl">rand</item>
                    <item type="gls" lang="en">give</item>
                    <item type="msa" lang="en">v</item>
                  </morph>
                  <morph type="suffix" guid="d7f713dd-e8cf-11d3-9764-00c04f186933">
                    <item type="txt" lang="wbl">-ən</item>
                    <item type="cf" lang="wbl">-ən</item>
                    <item type="hn" lang="wbl">2</item>
                    <item type="gls" lang="en">-1/3PL.NPST</item>
                  </morph>
                </morphemes>
                <item type="gls" lang="en">give</item>
              </word>
              <word>
                <item type="punct" lang="en">,</item>
              </word>
              <word guid="92e157bb-885a-46e8-b89c-a4b4a4eab235">
                <item type="txt" lang="wbl">tsav</item>
              </word>
              <word guid="ef3bcf0b-8f72-4409-9802-a6fb708af05c">
                <item type="txt" lang="wbl">simət</item>
              </word>
              <word guid="118114f5-a6cd-44b1-a0d2-27702a1c83a8">
                <item type="txt" lang="wbl">zarən</item>
                <morphemes>
                  <morph type="stem" guid="d7f713e8-e8cf-11d3-9764-00c04f186933">
                    <item type="txt" lang="wbl">zar</item>
                    <item type="cf" lang="wbl">zar</item>
                    <item type="hn" lang="wbl">2</item>
                    <item type="gls" lang="en">gold</item>
                    <item type="msa" lang="en">n</item>
                  </morph>
                  <morph type="suffix" guid="d7f713dd-e8cf-11d3-9764-00c04f186933">
                    <item type="txt" lang="wbl">-n</item>
                    <item type="cf" lang="wbl">-n</item>
                    <item type="gls" lang="en">-ABL</item>
                    <item type="msa" lang="en">n:(Case2)</item>
                  </morph>
                </morphemes>
                <item type="gls" lang="en">gold</item>
              </word>
              <word guid="0915d698-e1c5-4ceb-800b-42ac177b881c">
                <item type="txt" lang="wbl">ʃəxəs</item>
                <morphemes>
                  <morph type="stem" guid="d7f713e8-e8cf-11d3-9764-00c04f186933">
                    <item type="txt" lang="wbl">ʃəxs</item>
                    <item type="cf" lang="wbl">ʃəxs</item>
                    <item type="gls" lang="en">pass</item>
                    <item type="msa" lang="en">v</item>
                  </morph>
                  <morph type="suffix" guid="d7f713dd-e8cf-11d3-9764-00c04f186933">
                    <item type="txt" lang="wbl">-∅</item>
                    <item type="cf" lang="wbl">-∅</item>
                    <item type="gls" lang="en">-2SG.NPST</item>
                    <item type="msa" lang="en">v:Tns/Agr</item>
                  </morph>
                </morphemes>
                <item type="gls" lang="en">pass</item>
              </word>
              <word guid="d10a5c4f-6382-466f-b923-cc60d763189f">
                <item type="txt" lang="wbl">tsə</item>
                <morphemes>
                  <morph type="root" guid="d7f713e5-e8cf-11d3-9764-00c04f186933">
                    <item type="txt" lang="wbl">tsə</item>
                    <item type="cf" lang="wbl">tsə</item>
                    <item type="hn" lang="wbl">2</item>
                    <item type="gls" lang="en">from</item>
                    <item type="msa" lang="en">Loc/Dir</item>
                  </morph>
                </morphemes>
                <item type="gls" lang="en"></item>
              </word>
              <word guid="cdae057b-c68b-4383-a96e-79bc5f720fa3">
                <item type="txt" lang="wbl">maʐən</item>
                <morphemes>
                  <morph type="stem" guid="d7f713e8-e8cf-11d3-9764-00c04f186933">
                    <item type="txt" lang="wbl">maʐ</item>
                    <item type="cf" lang="wbl">maʐ</item>
                    <item type="gls" lang="en">1SG.OBL</item>
                    <item type="msa" lang="en">proobl</item>
                  </morph>
                  <morph type="suffix" guid="d7f713dd-e8cf-11d3-9764-00c04f186933">
                    <item type="txt" lang="wbl">-n</item>
                    <item type="cf" lang="wbl">-n</item>
                    <item type="gls" lang="en">-ABL</item>
                    <item type="msa" lang="en">n:(Case2)</item>
                  </morph>
                </morphemes>
              </word>
              <word guid="6651bdd0-3eb6-48f5-80fd-42147ed02378">
                <item type="txt" lang="wbl">dʒədoi</item>
                <morphemes>
                  <morph type="stem" guid="d7f713e8-e8cf-11d3-9764-00c04f186933">
                    <item type="txt" lang="wbl">dʒədo</item>
                    <item type="cf" lang="wbl">dʒida</item>
                    <item type="variantTypes" lang="en">+fr. var. of</item>
                    <item type="gls" lang="en">separate</item>
                    <item type="msa" lang="en">adj</item>
                  </morph>
                  <morph type="suffix" guid="d7f713dd-e8cf-11d3-9764-00c04f186933">
                    <item type="txt" lang="wbl">-i</item>
                    <item type="cf" lang="wbl">-iʝ</item>
                    <item type="variantTypes" lang="en">+fr. var. of</item>
                    <item type="gls" lang="en">-ness</item>
                    <item type="msa" lang="en">???&gt;n</item>
                  </morph>
                </morphemes>
                <item type="gls" lang="en">separate</item>
              </word>
              <word guid="a586ee26-9cca-4525-a790-3b423894eefc">
                <item type="txt" lang="wbl">mətsare</item>
              </word>
              <word>
                <item type="punct" lang="en">.</item>
              </word>
            </words>
            <item type="gls" lang="en">If the enemies give you their wealth, reject their wealth [and] don't be separate from me. </item>
          </phrase>
        </phrases>
      </paragraph>
    </paragraphs>
    <languages>
      <language lang="en" font="Times New Roman" vernacular="true" />
      <language lang="wbl" font="Charis SIL" vernacular="true" />
      <language lang="wbl-Qaaa-TJ-x-Zipa" font="Charis SIL" />
      <language lang="fr" font="Times New Roman" />
    </languages>
  </interlinear-text>
  
</document>
