<?xml version="1.0" encoding="utf-8"?>
<document version="2">
<interlinear-text guid="f5611035-197b-4b84-8758-0c2995fc7f22">
    <item type="title" lang="wbl">MSK ʃogɨn məborak wuz çanəm [2]</item>
    <paragraphs>
      <paragraph guid="32b7255e-df13-490e-a220-3be64f0f949a">
        <phrases>
          <phrase guid="904903e6-a0d4-483c-b3db-7ae09c2df247">
            <item type="segnum" lang="en">1</item>
            <words>
              <word guid="fd267316-c2da-4ad8-b5a6-e9bf4d26cb86">
                <item type="txt" lang="wbl">kɨli</item>
                <morphemes>
                  <morph type="stem" guid="d7f713e8-e8cf-11d3-9764-00c04f186933">
                    <item type="txt" lang="wbl">kɨl</item>
                    <item type="cf" lang="wbl">kɨl</item>
                    <item type="hn" lang="wbl">1</item>
                    <item type="gls" lang="en">everything</item>
                    <item type="msa" lang="en">n</item>
                  </morph>
                  <morph type="suffix" guid="d7f713dd-e8cf-11d3-9764-00c04f186933">
                    <item type="txt" lang="wbl">-i</item>
                    <item type="cf" lang="wbl">-i</item>
                    <item type="hn" lang="wbl">3</item>
                    <item type="gls" lang="en">-OBL</item>
                    <item type="msa" lang="en">n:(Case1)</item>
                  </morph>
                </morphemes>
                <item type="gls" lang="en">all</item>
              </word>
              <word guid="9497155f-5dd7-4344-9c07-ba1c6a0a774b">
                <item type="txt" lang="wbl">xalgər</item>
                <morphemes>
                  <morph type="stem" guid="d7f713e8-e8cf-11d3-9764-00c04f186933">
                    <item type="txt" lang="wbl">xalg</item>
                    <item type="cf" lang="wbl">xalg</item>
                    <item type="gls" lang="en">person</item>
                    <item type="msa" lang="en">n</item>
                  </morph>
                  <morph type="suffix" guid="d7f713dd-e8cf-11d3-9764-00c04f186933">
                    <item type="txt" lang="wbl">-ər</item>
                    <item type="cf" lang="wbl">-r</item>
                    <item type="gls" lang="en">-DAT</item>
                    <item type="msa" lang="en">n:(Case2)</item>
                  </morph>
                </morphemes>
              </word>
              <word guid="8954256d-7bf1-40ef-ba00-4335ef891f9a">
                <item type="txt" lang="wbl">dəm</item>
                <morphemes>
                  <morph type="stem" guid="d7f713e8-e8cf-11d3-9764-00c04f186933">
                    <item type="txt" lang="wbl">də</item>
                    <item type="cf" lang="wbl">də</item>
                    <item type="gls" lang="en">LOC</item>
                    <item type="msa" lang="en">Loc/Dir</item>
                  </morph>
                  <morph type="suffix" guid="d7f713dd-e8cf-11d3-9764-00c04f186933">
                    <item type="txt" lang="wbl">-m</item>
                    <item type="cf" lang="wbl">-m</item>
                    <item type="gls" lang="en">-PROX</item>
                    <item type="msa" lang="en">det:(Proximity)</item>
                  </morph>
                </morphemes>
              </word>
              <word guid="6f6b71c6-76a7-4d31-82fb-8d848a4695e0">
                <item type="txt" lang="wbl">dʒaon</item>
              </word>
              <word guid="6efb877b-2e49-4208-bf7d-96ea5125c91f">
                <item type="txt" lang="wbl">ʃogɨn</item>
                <morphemes>
                  <morph type="stem" guid="d7f713e8-e8cf-11d3-9764-00c04f186933">
                    <item type="txt" lang="wbl">ʃogɨn</item>
                    <item type="cf" lang="wbl">ʃogɨn</item>
                    <item type="gls" lang="en">new.year</item>
                    <item type="msa" lang="en">n</item>
                  </morph>
                </morphemes>
                <item type="gls" lang="en">new.year</item>
              </word>
              <word guid="27582798-0d34-4731-b9ea-2b264146c356">
                <item type="txt" lang="wbl">məborak</item>
                <morphemes>
                  <morph type="stem" guid="d7f713e8-e8cf-11d3-9764-00c04f186933">
                    <item type="txt" lang="wbl">məborak</item>
                    <item type="cf" lang="wbl">muborak</item>
                    <item type="variantTypes" lang="en">+fr. var. of</item>
                    <item type="gls" lang="en">blessed</item>
                    <item type="msa" lang="en">adj</item>
                  </morph>
                </morphemes>
                <item type="gls" lang="en">blessed</item>
              </word>
              <word guid="55ec1a4b-6db7-4857-b675-23d8db645245">
                <item type="txt" lang="wbl">wuz</item>
                <morphemes>
                  <morph type="stem" guid="d7f713e8-e8cf-11d3-9764-00c04f186933">
                    <item type="txt" lang="wbl">wuz</item>
                    <item type="cf" lang="wbl">wuz</item>
                    <item type="gls" lang="en">1SG.NOM</item>
                    <item type="msa" lang="en">pronom</item>
                  </morph>
                </morphemes>
                <item type="gls" lang="en">1SG.NOM</item>
              </word>
              <word guid="3a13fb1f-80ef-4061-aed1-d6740e89b4ee">
                <item type="txt" lang="wbl">çanəm</item>
                <morphemes>
                  <morph type="stem" guid="d7f713e8-e8cf-11d3-9764-00c04f186933">
                    <item type="txt" lang="wbl">çan</item>
                    <item type="cf" lang="wbl">çan</item>
                    <item type="gls" lang="en">say</item>
                    <item type="msa" lang="en">v</item>
                  </morph>
                  <morph type="suffix" guid="d7f713dd-e8cf-11d3-9764-00c04f186933">
                    <item type="txt" lang="wbl">-əm</item>
                    <item type="cf" lang="wbl">-əm</item>
                    <item type="hn" lang="wbl">1</item>
                    <item type="gls" lang="en">-1SG.NPST</item>
                    <item type="msa" lang="en">v:Tns/Agr</item>
                  </morph>
                </morphemes>
                <item type="gls" lang="en"></item>
              </word>
              <word>
                <item type="punct" lang="en">,</item>
              </word>
            </words>
            <item type="gls" lang="en">For all the people around the world, I wish [you all] a happy New Year,</item>
          </phrase>
        </phrases>
      </paragraph>
      <paragraph guid="2362cb84-eb5f-45b6-b5bb-e649f0890cbe">
        <phrases>
          <phrase guid="1b04f5e7-37ab-4373-818f-78f305ec4c64">
            <item type="segnum" lang="en">2</item>
            <words>
              <word guid="d10a5c4f-6382-466f-b923-cc60d763189f">
                <item type="txt" lang="wbl">tsə</item>
                <morphemes>
                  <morph type="root" guid="d7f713e5-e8cf-11d3-9764-00c04f186933">
                    <item type="txt" lang="wbl">tsə</item>
                    <item type="cf" lang="wbl">tsə</item>
                    <item type="hn" lang="wbl">2</item>
                    <item type="gls" lang="en">from</item>
                    <item type="msa" lang="en">Loc/Dir</item>
                  </morph>
                </morphemes>
                <item type="gls" lang="en"></item>
              </word>
              <word guid="d8a1bf1a-2662-426c-abe5-c6d3376fb7a4">
                <item type="txt" lang="wbl">xjarət</item>
              </word>
              <word guid="d10a5c4f-6382-466f-b923-cc60d763189f">
                <item type="txt" lang="wbl">tsə</item>
                <morphemes>
                  <morph type="root" guid="d7f713e5-e8cf-11d3-9764-00c04f186933">
                    <item type="txt" lang="wbl">tsə</item>
                    <item type="cf" lang="wbl">tsə</item>
                    <item type="hn" lang="wbl">2</item>
                    <item type="gls" lang="en">from</item>
                    <item type="msa" lang="en">Loc/Dir</item>
                  </morph>
                </morphemes>
                <item type="gls" lang="en"></item>
              </word>
              <word guid="1ae0c3fe-93ef-472d-b599-e83fbc630713">
                <item type="txt" lang="wbl">dʒwon</item>
                <morphemes>
                  <morph type="stem" guid="d7f713e8-e8cf-11d3-9764-00c04f186933">
                    <item type="txt" lang="wbl">dʒwon</item>
                    <item type="cf" lang="wbl">dʒuwon</item>
                    <item type="variantTypes" lang="en">+fr. var. of</item>
                    <item type="gls" lang="en">young</item>
                    <item type="msa" lang="en">adj</item>
                  </morph>
                </morphemes>
                <item type="gls" lang="en">young</item>
              </word>
              <word guid="6efb877b-2e49-4208-bf7d-96ea5125c91f">
                <item type="txt" lang="wbl">ʃogɨn</item>
                <morphemes>
                  <morph type="stem" guid="d7f713e8-e8cf-11d3-9764-00c04f186933">
                    <item type="txt" lang="wbl">ʃogɨn</item>
                    <item type="cf" lang="wbl">ʃogɨn</item>
                    <item type="gls" lang="en">new.year</item>
                    <item type="msa" lang="en">n</item>
                  </morph>
                </morphemes>
                <item type="gls" lang="en">new.year</item>
              </word>
              <word guid="27582798-0d34-4731-b9ea-2b264146c356">
                <item type="txt" lang="wbl">məborak</item>
                <morphemes>
                  <morph type="stem" guid="d7f713e8-e8cf-11d3-9764-00c04f186933">
                    <item type="txt" lang="wbl">məborak</item>
                    <item type="cf" lang="wbl">muborak</item>
                    <item type="variantTypes" lang="en">+fr. var. of</item>
                    <item type="gls" lang="en">blessed</item>
                    <item type="msa" lang="en">adj</item>
                  </morph>
                </morphemes>
                <item type="gls" lang="en">blessed</item>
              </word>
              <word guid="55ec1a4b-6db7-4857-b675-23d8db645245">
                <item type="txt" lang="wbl">wuz</item>
                <morphemes>
                  <morph type="stem" guid="d7f713e8-e8cf-11d3-9764-00c04f186933">
                    <item type="txt" lang="wbl">wuz</item>
                    <item type="cf" lang="wbl">wuz</item>
                    <item type="gls" lang="en">1SG.NOM</item>
                    <item type="msa" lang="en">pronom</item>
                  </morph>
                </morphemes>
                <item type="gls" lang="en">1SG.NOM</item>
              </word>
              <word guid="3a13fb1f-80ef-4061-aed1-d6740e89b4ee">
                <item type="txt" lang="wbl">çanəm</item>
                <morphemes>
                  <morph type="stem" guid="d7f713e8-e8cf-11d3-9764-00c04f186933">
                    <item type="txt" lang="wbl">çan</item>
                    <item type="cf" lang="wbl">çan</item>
                    <item type="gls" lang="en">say</item>
                    <item type="msa" lang="en">v</item>
                  </morph>
                  <morph type="suffix" guid="d7f713dd-e8cf-11d3-9764-00c04f186933">
                    <item type="txt" lang="wbl">-əm</item>
                    <item type="cf" lang="wbl">-əm</item>
                    <item type="hn" lang="wbl">1</item>
                    <item type="gls" lang="en">-1SG.NPST</item>
                    <item type="msa" lang="en">v:Tns/Agr</item>
                  </morph>
                </morphemes>
                <item type="gls" lang="en"></item>
              </word>
            </words>
            <item type="gls" lang="en">From old to young, I wish [you all] a happy New Year.</item>
          </phrase>
        </phrases>
      </paragraph>
      <paragraph guid="e6fc8bd8-5e9d-42be-ad3e-22e80ab02d34">
        <phrases>
          <phrase guid="fb29785e-a152-4268-b08e-f42ca94b749f">
            <item type="segnum" lang="en">3</item>
            <words>
              <word guid="d10a5c4f-6382-466f-b923-cc60d763189f">
                <item type="txt" lang="wbl">tsə</item>
                <morphemes>
                  <morph type="root" guid="d7f713e5-e8cf-11d3-9764-00c04f186933">
                    <item type="txt" lang="wbl">tsə</item>
                    <item type="cf" lang="wbl">tsə</item>
                    <item type="hn" lang="wbl">2</item>
                    <item type="gls" lang="en">from</item>
                    <item type="msa" lang="en">Loc/Dir</item>
                  </morph>
                </morphemes>
                <item type="gls" lang="en"></item>
              </word>
              <word guid="7097098d-f13f-4c50-ae80-355f07bcddfd">
                <item type="txt" lang="wbl">xdojən</item>
              </word>
              <word guid="07244fac-b3cd-48ee-881c-8aee2f086f58">
                <item type="txt" lang="wbl">xɨʃiʝət</item>
              </word>
              <word guid="66b75f8e-8bff-4230-a8f1-fa4dc5759e19">
                <item type="txt" lang="wbl">oromiʝ</item>
              </word>
              <word guid="55ec1a4b-6db7-4857-b675-23d8db645245">
                <item type="txt" lang="wbl">wuz</item>
                <morphemes>
                  <morph type="stem" guid="d7f713e8-e8cf-11d3-9764-00c04f186933">
                    <item type="txt" lang="wbl">wuz</item>
                    <item type="cf" lang="wbl">wuz</item>
                    <item type="gls" lang="en">1SG.NOM</item>
                    <item type="msa" lang="en">pronom</item>
                  </morph>
                </morphemes>
                <item type="gls" lang="en">1SG.NOM</item>
              </word>
              <word guid="e20b0348-bb60-4275-aad8-682cd468be27">
                <item type="txt" lang="wbl">xoiʃ</item>
                <morphemes>
                  <morph type="stem" guid="d7f713e8-e8cf-11d3-9764-00c04f186933">
                    <item type="txt" lang="wbl">xojiʃ</item>
                    <item type="cf" lang="wbl">xojiʃ</item>
                    <item type="gls" lang="en">desire</item>
                    <item type="msa" lang="en">n</item>
                  </morph>
                </morphemes>
                <item type="gls" lang="en">want</item>
              </word>
              <word guid="e7be2f5b-2bf0-46ca-b9c0-6e522610beb8">
                <item type="txt" lang="wbl">tsarəm</item>
                <morphemes>
                  <morph type="stem" guid="d7f713e8-e8cf-11d3-9764-00c04f186933">
                    <item type="txt" lang="wbl">tsar</item>
                    <item type="cf" lang="wbl">tsar</item>
                    <item type="gls" lang="en">do</item>
                    <item type="msa" lang="en">LightV</item>
                  </morph>
                  <morph type="suffix" guid="d7f713dd-e8cf-11d3-9764-00c04f186933">
                    <item type="txt" lang="wbl">-əm</item>
                    <item type="cf" lang="wbl">-əm</item>
                    <item type="hn" lang="wbl">1</item>
                    <item type="gls" lang="en">-1SG.NPST</item>
                    <item type="msa" lang="en">v:Tns/Agr</item>
                  </morph>
                </morphemes>
                <item type="gls" lang="en">do</item>
              </word>
              <word>
                <item type="punct" lang="en">,</item>
              </word>
            </words>
            <item type="gls" lang="en">From God my wish is happiness and peace. </item>
          </phrase>
        </phrases>
      </paragraph>
      <paragraph guid="36a53171-4f33-4869-92d2-a4a884b59525">
        <phrases>
          <phrase guid="7bc9c0cd-b74a-4515-bc65-18cd3076461b">
            <item type="segnum" lang="en">4</item>
            <words>
              <word guid="29aca3fe-5e50-4b4e-9b90-8d797b43a5c3">
                <item type="txt" lang="wbl">broi</item>
                <morphemes>
                  <morph type="stem" guid="d7f713e8-e8cf-11d3-9764-00c04f186933">
                    <item type="txt" lang="wbl">bəroji</item>
                    <item type="cf" lang="wbl">baroji</item>
                    <item type="variantTypes" lang="en">+fr. var. of</item>
                    <item type="gls" lang="en">for</item>
                    <item type="msa" lang="en">comp</item>
                  </morph>
                </morphemes>
                <item type="gls" lang="en">for (Persian)</item>
              </word>
              <word guid="79e079e0-53e4-4836-bca9-9e2fba3e92cb">
                <item type="txt" lang="wbl">ar</item>
                <morphemes>
                  <morph type="prefix" guid="d7f713db-e8cf-11d3-9764-00c04f186933">
                    <item type="txt" lang="wbl">a-</item>
                    <item type="cf" lang="wbl">a-</item>
                    <item type="gls" lang="en">EMPH-</item>
                    <item type="msa" lang="en">det&gt;det</item>
                  </morph>
                  <morph type="stem" guid="d7f713e8-e8cf-11d3-9764-00c04f186933">
                    <item type="txt" lang="wbl">ər</item>
                    <item type="cf" lang="wbl">rə</item>
                    <item type="variantTypes" lang="en">+fr. var. of</item>
                    <item type="gls" lang="en">ALL</item>
                    <item type="msa" lang="en">Loc/Dir</item>
                  </morph>
                </morphemes>
                <item type="gls" lang="en"></item>
              </word>
              <word guid="3baeaf7d-e18c-40d2-a5e4-9b1274104921">
                <item type="txt" lang="wbl">jak</item>
                <morphemes>
                  <morph type="stem" guid="d7f713e8-e8cf-11d3-9764-00c04f186933">
                    <item type="txt" lang="wbl">jak</item>
                    <item type="cf" lang="wbl">jak</item>
                    <item type="hn" lang="wbl">2</item>
                    <item type="gls" lang="en">one.PER</item>
                    <item type="msa" lang="en">num</item>
                  </morph>
                </morphemes>
              </word>
              <word guid="0cce9a90-6a8e-42df-b7ed-1a1ea83fcb47">
                <item type="txt" lang="wbl">xonadon</item>
              </word>
              <word>
                <item type="punct" lang="en">,</item>
              </word>
              <word guid="6efb877b-2e49-4208-bf7d-96ea5125c91f">
                <item type="txt" lang="wbl">ʃogɨn</item>
                <morphemes>
                  <morph type="stem" guid="d7f713e8-e8cf-11d3-9764-00c04f186933">
                    <item type="txt" lang="wbl">ʃogɨn</item>
                    <item type="cf" lang="wbl">ʃogɨn</item>
                    <item type="gls" lang="en">new.year</item>
                    <item type="msa" lang="en">n</item>
                  </morph>
                </morphemes>
                <item type="gls" lang="en">new.year</item>
              </word>
              <word guid="27582798-0d34-4731-b9ea-2b264146c356">
                <item type="txt" lang="wbl">məborak</item>
                <morphemes>
                  <morph type="stem" guid="d7f713e8-e8cf-11d3-9764-00c04f186933">
                    <item type="txt" lang="wbl">məborak</item>
                    <item type="cf" lang="wbl">muborak</item>
                    <item type="variantTypes" lang="en">+fr. var. of</item>
                    <item type="gls" lang="en">blessed</item>
                    <item type="msa" lang="en">adj</item>
                  </morph>
                </morphemes>
                <item type="gls" lang="en">blessed</item>
              </word>
              <word guid="55ec1a4b-6db7-4857-b675-23d8db645245">
                <item type="txt" lang="wbl">wuz</item>
                <morphemes>
                  <morph type="stem" guid="d7f713e8-e8cf-11d3-9764-00c04f186933">
                    <item type="txt" lang="wbl">wuz</item>
                    <item type="cf" lang="wbl">wuz</item>
                    <item type="gls" lang="en">1SG.NOM</item>
                    <item type="msa" lang="en">pronom</item>
                  </morph>
                </morphemes>
                <item type="gls" lang="en">1SG.NOM</item>
              </word>
              <word guid="3a13fb1f-80ef-4061-aed1-d6740e89b4ee">
                <item type="txt" lang="wbl">çanəm</item>
                <morphemes>
                  <morph type="stem" guid="d7f713e8-e8cf-11d3-9764-00c04f186933">
                    <item type="txt" lang="wbl">çan</item>
                    <item type="cf" lang="wbl">çan</item>
                    <item type="gls" lang="en">say</item>
                    <item type="msa" lang="en">v</item>
                  </morph>
                  <morph type="suffix" guid="d7f713dd-e8cf-11d3-9764-00c04f186933">
                    <item type="txt" lang="wbl">-əm</item>
                    <item type="cf" lang="wbl">-əm</item>
                    <item type="hn" lang="wbl">1</item>
                    <item type="gls" lang="en">-1SG.NPST</item>
                    <item type="msa" lang="en">v:Tns/Agr</item>
                  </morph>
                </morphemes>
                <item type="gls" lang="en"></item>
              </word>
              <word>
                <item type="punct" lang="en">.</item>
              </word>
            </words>
            <item type="gls" lang="en">To each family individually, I wish them a happy New Year. </item>
          </phrase>
        </phrases>
      </paragraph>
      <paragraph guid="ad219a89-8428-449b-8c83-2d6c9eb03d6f">
        <phrases>
          <phrase guid="a83f2a9a-f00e-4e45-a839-67eb56d93fbc">
            <item type="segnum" lang="en">5</item>
            <words>
              <word guid="d10a5c4f-6382-466f-b923-cc60d763189f">
                <item type="txt" lang="wbl">tsə</item>
                <morphemes>
                  <morph type="root" guid="d7f713e5-e8cf-11d3-9764-00c04f186933">
                    <item type="txt" lang="wbl">tsə</item>
                    <item type="cf" lang="wbl">tsə</item>
                    <item type="hn" lang="wbl">2</item>
                    <item type="gls" lang="en">from</item>
                    <item type="msa" lang="en">Loc/Dir</item>
                  </morph>
                </morphemes>
                <item type="gls" lang="en"></item>
              </word>
              <word guid="759fa825-4259-414d-b489-7ecd7d754ef9">
                <item type="txt" lang="wbl">qdami</item>
              </word>
              <word guid="94a7f42c-7009-4e9b-a09b-ff5fbfca948c">
                <item type="txt" lang="wbl">nawbəorən</item>
              </word>
              <word guid="a7f0d2f1-465b-4113-9a09-b63362786b50">
                <item type="txt" lang="wbl">wost</item>
                <morphemes>
                  <morph type="stem" guid="d7f713e8-e8cf-11d3-9764-00c04f186933">
                    <item type="txt" lang="wbl">wos</item>
                    <item type="cf" lang="wbl">wots</item>
                    <item type="gls" lang="en">become</item>
                    <item type="msa" lang="en">v</item>
                  </morph>
                  <morph type="suffix" guid="d7f713dd-e8cf-11d3-9764-00c04f186933">
                    <item type="txt" lang="wbl">-t</item>
                    <item type="cf" lang="wbl">-t</item>
                    <item type="hn" lang="wbl">1</item>
                    <item type="gls" lang="en">-3SG.NPST</item>
                    <item type="msa" lang="en">v:Tns/Agr</item>
                  </morph>
                </morphemes>
                <item type="gls" lang="en">become</item>
              </word>
              <word guid="30d2ff3b-36a6-4bea-824b-f9eaee52291b">
                <item type="txt" lang="wbl">gɨlzor</item>
                <morphemes>
                  <morph type="phrase" guid="a23b6faa-1052-4f4d-984b-4b338bdaf95f">
                    <item type="txt" lang="wbl">gɨlzor</item>
                    <item type="cf" lang="wbl">gɨli gəlzor</item>
                    <item type="variantTypes" lang="en">+fr. var. of</item>
                    <item type="gls" lang="en">garden</item>
                    <item type="msa" lang="en">n</item>
                  </morph>
                </morphemes>
                <item type="gls" lang="en">garden</item>
              </word>
              <word guid="1ce66bd6-456d-4f92-82b4-8ee43f6dfdb3">
                <item type="txt" lang="wbl">jəm</item>
                <morphemes>
                  <morph type="stem" guid="d7f713e8-e8cf-11d3-9764-00c04f186933">
                    <item type="txt" lang="wbl">j</item>
                    <item type="cf" lang="wbl">j</item>
                    <item type="gls" lang="en">DEM</item>
                    <item type="msa" lang="en">det</item>
                  </morph>
                  <morph type="suffix" guid="d7f713dd-e8cf-11d3-9764-00c04f186933">
                    <item type="txt" lang="wbl">-m</item>
                    <item type="cf" lang="wbl">-m</item>
                    <item type="gls" lang="en">-PROX</item>
                    <item type="msa" lang="en">det:(Proximity)</item>
                  </morph>
                </morphemes>
                <item type="gls" lang="en"></item>
              </word>
              <word guid="6f6b71c6-76a7-4d31-82fb-8d848a4695e0">
                <item type="txt" lang="wbl">dʒaon</item>
              </word>
              <word>
                <item type="punct" lang="en">,</item>
              </word>
            </words>
            <item type="gls" lang="en">Because the beginning of spring is coming, this world will become all flowers [a garden].</item>
          </phrase>
        </phrases>
      </paragraph>
      <paragraph guid="ca0d8ecb-9ffd-4792-aaf0-f760c7cd5ed7">
        <phrases>
          <phrase guid="b3ef542d-a427-42b2-b713-ed44515a5401">
            <item type="segnum" lang="en">6</item>
            <words>
              <word guid="913b657f-06e3-46b8-85b6-8c1b8c1742ad">
                <item type="txt" lang="wbl">mərdɨmi</item>
              </word>
              <word guid="d11284c0-a0c6-4029-81a4-d59c5a92f19f">
                <item type="txt" lang="wbl">bomi</item>
              </word>
              <word guid="6f6b71c6-76a7-4d31-82fb-8d848a4695e0">
                <item type="txt" lang="wbl">dʒaon</item>
              </word>
              <word>
                <item type="punct" lang="en">,</item>
              </word>
              <word guid="6efb877b-2e49-4208-bf7d-96ea5125c91f">
                <item type="txt" lang="wbl">ʃogɨn</item>
                <morphemes>
                  <morph type="stem" guid="d7f713e8-e8cf-11d3-9764-00c04f186933">
                    <item type="txt" lang="wbl">ʃogɨn</item>
                    <item type="cf" lang="wbl">ʃogɨn</item>
                    <item type="gls" lang="en">new.year</item>
                    <item type="msa" lang="en">n</item>
                  </morph>
                </morphemes>
                <item type="gls" lang="en">new.year</item>
              </word>
              <word guid="27582798-0d34-4731-b9ea-2b264146c356">
                <item type="txt" lang="wbl">məborak</item>
                <morphemes>
                  <morph type="stem" guid="d7f713e8-e8cf-11d3-9764-00c04f186933">
                    <item type="txt" lang="wbl">məborak</item>
                    <item type="cf" lang="wbl">muborak</item>
                    <item type="variantTypes" lang="en">+fr. var. of</item>
                    <item type="gls" lang="en">blessed</item>
                    <item type="msa" lang="en">adj</item>
                  </morph>
                </morphemes>
                <item type="gls" lang="en">blessed</item>
              </word>
              <word guid="55ec1a4b-6db7-4857-b675-23d8db645245">
                <item type="txt" lang="wbl">wuz</item>
                <morphemes>
                  <morph type="stem" guid="d7f713e8-e8cf-11d3-9764-00c04f186933">
                    <item type="txt" lang="wbl">wuz</item>
                    <item type="cf" lang="wbl">wuz</item>
                    <item type="gls" lang="en">1SG.NOM</item>
                    <item type="msa" lang="en">pronom</item>
                  </morph>
                </morphemes>
                <item type="gls" lang="en">1SG.NOM</item>
              </word>
              <word guid="1bfd9813-1ee3-4952-af96-9f873c0ae494">
                <item type="txt" lang="wbl">çanəmm</item>
              </word>
              <word>
                <item type="punct" lang="en">.</item>
              </word>
            </words>
            <item type="gls" lang="en">To the people of the roof of the world, I wish you a happy New Year.</item>
          </phrase>
        </phrases>
      </paragraph>
      <paragraph guid="746a9238-a82e-4d21-b1e8-fdebcbd0c02c">
        <phrases>
          <phrase guid="4ab2272f-8d88-419d-addd-3c6e049529cb">
            <item type="segnum" lang="en">7</item>
            <words>
              <word guid="79e079e0-53e4-4836-bca9-9e2fba3e92cb">
                <item type="txt" lang="wbl">ar</item>
                <morphemes>
                  <morph type="prefix" guid="d7f713db-e8cf-11d3-9764-00c04f186933">
                    <item type="txt" lang="wbl">a-</item>
                    <item type="cf" lang="wbl">a-</item>
                    <item type="gls" lang="en">EMPH-</item>
                    <item type="msa" lang="en">det&gt;det</item>
                  </morph>
                  <morph type="stem" guid="d7f713e8-e8cf-11d3-9764-00c04f186933">
                    <item type="txt" lang="wbl">ər</item>
                    <item type="cf" lang="wbl">rə</item>
                    <item type="variantTypes" lang="en">+fr. var. of</item>
                    <item type="gls" lang="en">ALL</item>
                    <item type="msa" lang="en">Loc/Dir</item>
                  </morph>
                </morphemes>
                <item type="gls" lang="en"></item>
              </word>
              <word guid="14618ad4-2ab0-4907-8dda-f8ed1a13bb8f">
                <item type="txt" lang="wbl">marizət</item>
              </word>
              <word guid="04c77e8e-8020-4112-8729-87cd46958ef9">
                <item type="txt" lang="wbl">ofati</item>
                <morphemes>
                  <morph type="stem" guid="d7f713e8-e8cf-11d3-9764-00c04f186933">
                    <item type="txt" lang="wbl">ofat</item>
                    <item type="cf" lang="wbl">ofat</item>
                    <item type="gls" lang="en">disaster</item>
                    <item type="msa" lang="en">n</item>
                  </morph>
                  <morph type="suffix" guid="d7f713dd-e8cf-11d3-9764-00c04f186933">
                    <item type="txt" lang="wbl">-i</item>
                    <item type="cf" lang="wbl">-i</item>
                    <item type="hn" lang="wbl">3</item>
                    <item type="gls" lang="en">-OBL</item>
                    <item type="msa" lang="en">n:(Case1)</item>
                  </morph>
                </morphemes>
              </word>
              <word guid="b2491aff-3283-4895-bd78-e0fc0c03be39">
                <item type="txt" lang="wbl">məwloi</item>
              </word>
              <word guid="adcac19c-fac6-4fd9-916b-931e94d2b085">
                <item type="txt" lang="wbl">aq</item>
                <morphemes>
                  <morph type="stem" guid="d7f713e8-e8cf-11d3-9764-00c04f186933">
                    <item type="txt" lang="wbl">aq</item>
                    <item type="cf" lang="wbl">haq</item>
                    <item type="variantTypes" lang="en">+fr. var. of</item>
                    <item type="gls" lang="en">right</item>
                    <item type="msa" lang="en">n</item>
                  </morph>
                </morphemes>
                <item type="gls" lang="en">right</item>
              </word>
              <word guid="909d4d66-4519-4a61-9626-7fd40379f993">
                <item type="txt" lang="wbl">ʃogɨni</item>
              </word>
              <word guid="64eece8c-cfba-4b2e-96e1-de1aea34b106">
                <item type="txt" lang="wbl">goçt</item>
                <morphemes>
                  <morph type="stem" guid="d7f713e8-e8cf-11d3-9764-00c04f186933">
                    <item type="txt" lang="wbl">goç</item>
                    <item type="cf" lang="wbl">goç</item>
                    <item type="gls" lang="en">make</item>
                    <item type="msa" lang="en">v</item>
                  </morph>
                  <morph type="suffix" guid="d7f713dd-e8cf-11d3-9764-00c04f186933">
                    <item type="txt" lang="wbl">-t</item>
                    <item type="cf" lang="wbl">-t</item>
                    <item type="hn" lang="wbl">1</item>
                    <item type="gls" lang="en">-3SG.NPST</item>
                    <item type="msa" lang="en">v:Tns/Agr</item>
                  </morph>
                </morphemes>
              </word>
              <word>
                <item type="punct" lang="en">,</item>
              </word>
            </words>
            <item type="gls" lang="en">For all the sickness and disaster, may Mawlo make all happiness,</item>
          </phrase>
        </phrases>
      </paragraph>
      <paragraph guid="4ffb3d39-c25c-4332-9cd6-c31135bc4b92">
        <phrases>
          <phrase guid="9a1ff58c-fd1e-46c2-8404-f4048553e0b0">
            <item type="segnum" lang="en">8.1</item>
            <words>
              <word guid="cdd3249f-60ee-4616-860a-6cf07610f481">
                <item type="txt" lang="wbl">jət</item>
                <morphemes>
                  <morph type="stem" guid="d7f713e8-e8cf-11d3-9764-00c04f186933">
                    <item type="txt" lang="wbl">j</item>
                    <item type="cf" lang="wbl">j</item>
                    <item type="gls" lang="en">DEM</item>
                    <item type="msa" lang="en">det</item>
                  </morph>
                  <morph type="suffix" guid="d7f713dd-e8cf-11d3-9764-00c04f186933">
                    <item type="txt" lang="wbl">-t</item>
                    <item type="cf" lang="wbl">-t</item>
                    <item type="hn" lang="wbl">3</item>
                    <item type="gls" lang="en">-DIST</item>
                    <item type="msa" lang="en">det:(Proximity)</item>
                  </morph>
                </morphemes>
                <item type="gls" lang="en">DEM</item>
              </word>
              <word guid="de692be1-aa13-4e86-9976-ecfeedecc20d">
                <item type="txt" lang="wbl">ʐɨnən</item>
                <morphemes>
                  <morph type="stem" guid="d7f713e8-e8cf-11d3-9764-00c04f186933">
                    <item type="txt" lang="wbl">ʐɨ</item>
                    <item type="cf" lang="wbl">ʐɨ</item>
                    <item type="gls" lang="en">1SG.GEN</item>
                    <item type="msa" lang="en">poss</item>
                  </morph>
                  <morph type="suffix" guid="d7f713dd-e8cf-11d3-9764-00c04f186933">
                    <item type="txt" lang="wbl">-nən</item>
                    <item type="cf" lang="wbl">-n</item>
                    <item type="gls" lang="en">-ABL</item>
                    <item type="msa" lang="en">n:(Case2)</item>
                  </morph>
                </morphemes>
                <item type="gls" lang="en">mine</item>
              </word>
              <word guid="0fac7471-9888-4043-b438-73762e2daa97">
                <item type="txt" lang="wbl">ʐɨ</item>
                <morphemes>
                  <morph type="stem" guid="d7f713e8-e8cf-11d3-9764-00c04f186933">
                    <item type="txt" lang="wbl">ʐɨ</item>
                    <item type="cf" lang="wbl">ʐɨ</item>
                    <item type="gls" lang="en">1SG.GEN</item>
                    <item type="msa" lang="en">poss</item>
                  </morph>
                </morphemes>
                <item type="gls" lang="en">my</item>
              </word>
              <word guid="ed07a5ff-03d9-41be-8676-e417923febb4">
                <item type="txt" lang="wbl">armon</item>
                <morphemes>
                  <morph type="stem" guid="d7f713e8-e8cf-11d3-9764-00c04f186933">
                    <item type="txt" lang="wbl">armon</item>
                    <item type="cf" lang="wbl">armon</item>
                    <item type="gls" lang="en">desire</item>
                    <item type="msa" lang="en">n</item>
                  </morph>
                </morphemes>
                <item type="gls" lang="en">desire</item>
              </word>
              <word>
                <item type="punct" lang="en">.</item>
              </word>
            </words>
            <item type="gls" lang="en">That is my only dream, </item>
          </phrase>
          <phrase guid="2a2ce979-b116-4374-9aa7-68389087de36">
            <item type="segnum" lang="en">8.2</item>
            <words>
              <word guid="6efb877b-2e49-4208-bf7d-96ea5125c91f">
                <item type="txt" lang="wbl">ʃogɨn</item>
                <morphemes>
                  <morph type="stem" guid="d7f713e8-e8cf-11d3-9764-00c04f186933">
                    <item type="txt" lang="wbl">ʃogɨn</item>
                    <item type="cf" lang="wbl">ʃogɨn</item>
                    <item type="gls" lang="en">new.year</item>
                    <item type="msa" lang="en">n</item>
                  </morph>
                </morphemes>
                <item type="gls" lang="en">new.year</item>
              </word>
              <word guid="27582798-0d34-4731-b9ea-2b264146c356">
                <item type="txt" lang="wbl">məborak</item>
                <morphemes>
                  <morph type="stem" guid="d7f713e8-e8cf-11d3-9764-00c04f186933">
                    <item type="txt" lang="wbl">məborak</item>
                    <item type="cf" lang="wbl">muborak</item>
                    <item type="variantTypes" lang="en">+fr. var. of</item>
                    <item type="gls" lang="en">blessed</item>
                    <item type="msa" lang="en">adj</item>
                  </morph>
                </morphemes>
                <item type="gls" lang="en">blessed</item>
              </word>
              <word guid="55ec1a4b-6db7-4857-b675-23d8db645245">
                <item type="txt" lang="wbl">wuz</item>
                <morphemes>
                  <morph type="stem" guid="d7f713e8-e8cf-11d3-9764-00c04f186933">
                    <item type="txt" lang="wbl">wuz</item>
                    <item type="cf" lang="wbl">wuz</item>
                    <item type="gls" lang="en">1SG.NOM</item>
                    <item type="msa" lang="en">pronom</item>
                  </morph>
                </morphemes>
                <item type="gls" lang="en">1SG.NOM</item>
              </word>
              <word guid="3a13fb1f-80ef-4061-aed1-d6740e89b4ee">
                <item type="txt" lang="wbl">çanəm</item>
                <morphemes>
                  <morph type="stem" guid="d7f713e8-e8cf-11d3-9764-00c04f186933">
                    <item type="txt" lang="wbl">çan</item>
                    <item type="cf" lang="wbl">çan</item>
                    <item type="gls" lang="en">say</item>
                    <item type="msa" lang="en">v</item>
                  </morph>
                  <morph type="suffix" guid="d7f713dd-e8cf-11d3-9764-00c04f186933">
                    <item type="txt" lang="wbl">-əm</item>
                    <item type="cf" lang="wbl">-əm</item>
                    <item type="hn" lang="wbl">1</item>
                    <item type="gls" lang="en">-1SG.NPST</item>
                    <item type="msa" lang="en">v:Tns/Agr</item>
                  </morph>
                </morphemes>
                <item type="gls" lang="en"></item>
              </word>
              <word>
                <item type="punct" lang="en">.</item>
              </word>
            </words>
            <item type="gls" lang="en">I wish you all happy New Year. </item>
          </phrase>
        </phrases>
      </paragraph>
      <paragraph guid="2fa1feb1-e201-4d10-b071-a152060d7323">
        <phrases>
          <phrase guid="14a2c6ec-c70a-4d53-bd04-6cbd100cd453">
            <item type="segnum" lang="en">9</item>
            <words>
              <word guid="dad24fd9-7512-49d4-a1d1-2f0f74649d4e">
                <item type="txt" lang="wbl">bɨlbɨləm</item>
                <morphemes>
                  <morph type="stem" guid="d7f713e8-e8cf-11d3-9764-00c04f186933">
                    <item type="txt" lang="wbl">bɨlbɨl</item>
                    <item type="cf" lang="wbl">bɨlbɨl</item>
                    <item type="gls" lang="en">nightingale</item>
                    <item type="msa" lang="en">n</item>
                  </morph>
                  <morph>
                    <item type="txt" lang="wbl">əm</item>
                  </morph>
                </morphemes>
              </word>
              <word guid="ecefe5ec-3bd6-4e3c-bbe5-9c2597039449">
                <item type="txt" lang="wbl">pərsti</item>
                <morphemes>
                  <morph type="stem" guid="d7f713e8-e8cf-11d3-9764-00c04f186933">
                    <item type="txt" lang="wbl">pərs</item>
                    <item type="cf" lang="wbl">pers</item>
                    <item type="gls" lang="en">ask</item>
                    <item type="msa" lang="en">v</item>
                  </morph>
                  <morph type="suffix" guid="d7f713dd-e8cf-11d3-9764-00c04f186933">
                    <item type="txt" lang="wbl">-t</item>
                    <item type="cf" lang="wbl">-t</item>
                    <item type="hn" lang="wbl">2</item>
                    <item type="gls" lang="en">-PST</item>
                    <item type="msa" lang="en">v:Pst1</item>
                  </morph>
                  <morph type="suffix" guid="d7f713dd-e8cf-11d3-9764-00c04f186933">
                    <item type="txt" lang="wbl">-i</item>
                    <item type="cf" lang="wbl">-i</item>
                    <item type="hn" lang="wbl">1</item>
                    <item type="gls" lang="en">-PST</item>
                    <item type="msa" lang="en">v:(Pst2)</item>
                  </morph>
                </morphemes>
              </word>
              <word guid="b5bc835f-5abf-4252-a2da-aca60e317c69">
                <item type="txt" lang="wbl">tsərər</item>
                <morphemes>
                  <morph type="stem" guid="d7f713e8-e8cf-11d3-9764-00c04f186933">
                    <item type="txt" lang="wbl">tsə</item>
                    <item type="cf" lang="wbl">tsə</item>
                    <item type="hn" lang="wbl">3</item>
                    <item type="gls" lang="en">QSTN</item>
                    <item type="msa" lang="en">adv</item>
                  </morph>
                  <morph type="suffix" guid="d7f713dd-e8cf-11d3-9764-00c04f186933">
                    <item type="txt" lang="wbl">-rər</item>
                    <item type="cf" lang="wbl">-r</item>
                    <item type="gls" lang="en">-DAT</item>
                    <item type="msa" lang="en">n:(Case2)</item>
                  </morph>
                </morphemes>
                <item type="gls" lang="en">QSTN</item>
              </word>
              <word guid="6ec7f473-3e3f-4428-8493-827bd6ade6c6">
                <item type="txt" lang="wbl">tu</item>
                <morphemes>
                  <morph type="stem" guid="d7f713e8-e8cf-11d3-9764-00c04f186933">
                    <item type="txt" lang="wbl">tu</item>
                    <item type="cf" lang="wbl">tu</item>
                    <item type="gls" lang="en">2SG.NOM</item>
                    <item type="msa" lang="en">pro</item>
                  </morph>
                </morphemes>
                <item type="gls" lang="en">you</item>
              </word>
              <word guid="8954256d-7bf1-40ef-ba00-4335ef891f9a">
                <item type="txt" lang="wbl">dəm</item>
                <morphemes>
                  <morph type="stem" guid="d7f713e8-e8cf-11d3-9764-00c04f186933">
                    <item type="txt" lang="wbl">də</item>
                    <item type="cf" lang="wbl">də</item>
                    <item type="gls" lang="en">LOC</item>
                    <item type="msa" lang="en">Loc/Dir</item>
                  </morph>
                  <morph type="suffix" guid="d7f713dd-e8cf-11d3-9764-00c04f186933">
                    <item type="txt" lang="wbl">-m</item>
                    <item type="cf" lang="wbl">-m</item>
                    <item type="gls" lang="en">-PROX</item>
                    <item type="msa" lang="en">det:(Proximity)</item>
                  </morph>
                </morphemes>
              </word>
              <word guid="af8a5e09-3b6c-433b-89c0-2d55258f7de3">
                <item type="txt" lang="wbl">bəor</item>
                <morphemes>
                  <morph type="stem" guid="d7f713e8-e8cf-11d3-9764-00c04f186933">
                    <item type="txt" lang="wbl">bəor</item>
                    <item type="cf" lang="wbl">bahor</item>
                    <item type="variantTypes" lang="en">+fr. var. of</item>
                    <item type="gls" lang="en">spring</item>
                    <item type="msa" lang="en">n</item>
                  </morph>
                </morphemes>
                <item type="gls" lang="en">spring</item>
              </word>
              <word guid="47ea2b2f-793c-4bf8-82f4-548e9c3d9bf6">
                <item type="txt" lang="wbl">nolaʂ</item>
                <morphemes>
                  <morph type="stem" guid="d7f713e8-e8cf-11d3-9764-00c04f186933">
                    <item type="txt" lang="wbl">nola</item>
                    <item type="cf" lang="wbl">nola</item>
                    <item type="gls" lang="en">wailing</item>
                    <item type="msa" lang="en">n</item>
                  </morph>
                  <morph>
                    <item type="txt" lang="wbl">ʂ</item>
                  </morph>
                </morphemes>
              </word>
              <word guid="2c54c3ee-87df-487b-b78c-739c9d2daed7">
                <item type="txt" lang="wbl">tsar</item>
                <morphemes>
                  <morph type="stem" guid="d7f713e8-e8cf-11d3-9764-00c04f186933">
                    <item type="txt" lang="wbl">tsar</item>
                    <item type="cf" lang="wbl">tsar</item>
                    <item type="gls" lang="en">do</item>
                    <item type="msa" lang="en">LightV</item>
                  </morph>
                  <morph type="suffix" guid="d7f713dd-e8cf-11d3-9764-00c04f186933">
                    <item type="txt" lang="wbl">-∅</item>
                    <item type="cf" lang="wbl">-∅</item>
                    <item type="gls" lang="en">-2SG.NPST</item>
                    <item type="msa" lang="en">v:Tns/Agr</item>
                  </morph>
                </morphemes>
              </word>
              <word>
                <item type="punct" lang="en">.</item>
              </word>
            </words>
            <item type="gls" lang="en">I asked the nightingale, [why] are you wailing?</item>
          </phrase>
        </phrases>
      </paragraph>
      <paragraph guid="8405cc7e-6fbd-42ae-87de-91c791463ef8">
        <phrases>
          <phrase guid="ecbbc036-89bc-484f-9f28-1b21ffd50f20">
            <item type="segnum" lang="en">10</item>
            <words>
              <word guid="0520f576-c206-47d3-aaa7-ef12e6fbf476">
                <item type="txt" lang="wbl">çati</item>
                <morphemes>
                  <morph type="stem" guid="d7f713e8-e8cf-11d3-9764-00c04f186933">
                    <item type="txt" lang="wbl">ça</item>
                    <item type="cf" lang="wbl">çan</item>
                    <item type="gls" lang="en">say</item>
                    <item type="msa" lang="en">v</item>
                  </morph>
                  <morph type="suffix" guid="d7f713dd-e8cf-11d3-9764-00c04f186933">
                    <item type="txt" lang="wbl">-t</item>
                    <item type="cf" lang="wbl">-t</item>
                    <item type="hn" lang="wbl">2</item>
                    <item type="gls" lang="en">-PST</item>
                    <item type="msa" lang="en">v:Pst1</item>
                  </morph>
                  <morph type="suffix" guid="d7f713dd-e8cf-11d3-9764-00c04f186933">
                    <item type="txt" lang="wbl">-i</item>
                    <item type="cf" lang="wbl">-i</item>
                    <item type="hn" lang="wbl">1</item>
                    <item type="gls" lang="en">-PST</item>
                    <item type="msa" lang="en">v:(Pst2)</item>
                  </morph>
                </morphemes>
                <item type="gls" lang="en"></item>
              </word>
              <word guid="e53cc5c4-b8fe-45c0-8cf9-5e3db0326212">
                <item type="txt" lang="wbl">savərk</item>
                <morphemes>
                  <morph type="stem" guid="d7f713e8-e8cf-11d3-9764-00c04f186933">
                    <item type="txt" lang="wbl">sa</item>
                    <item type="cf" lang="wbl">sa</item>
                    <item type="hn" lang="wbl">2</item>
                    <item type="gls" lang="en">2PL</item>
                    <item type="msa" lang="en">pro</item>
                  </morph>
                  <morph type="suffix" guid="d7f713dd-e8cf-11d3-9764-00c04f186933">
                    <item type="txt" lang="wbl">-v</item>
                    <item type="cf" lang="wbl">-v</item>
                    <item type="gls" lang="en">-OBL.PL</item>
                    <item type="msa" lang="en">n:(Number)</item>
                  </morph>
                  <morph type="suffix" guid="d7f713dd-e8cf-11d3-9764-00c04f186933">
                    <item type="txt" lang="wbl">-ərk</item>
                    <item type="cf" lang="wbl">-r</item>
                    <item type="gls" lang="en">-DAT</item>
                    <item type="msa" lang="en">n:(Case2)</item>
                  </morph>
                </morphemes>
              </word>
              <word>
                <item type="punct" lang="en">,</item>
              </word>
              <word guid="3d886f3a-dd66-474a-aa62-6f2a8132ea26">
                <item type="txt" lang="wbl">oʃiqon</item>
              </word>
              <word>
                <item type="punct" lang="en">,</item>
              </word>
              <word guid="6efb877b-2e49-4208-bf7d-96ea5125c91f">
                <item type="txt" lang="wbl">ʃogɨn</item>
                <morphemes>
                  <morph type="stem" guid="d7f713e8-e8cf-11d3-9764-00c04f186933">
                    <item type="txt" lang="wbl">ʃogɨn</item>
                    <item type="cf" lang="wbl">ʃogɨn</item>
                    <item type="gls" lang="en">new.year</item>
                    <item type="msa" lang="en">n</item>
                  </morph>
                </morphemes>
                <item type="gls" lang="en">new.year</item>
              </word>
              <word guid="27582798-0d34-4731-b9ea-2b264146c356">
                <item type="txt" lang="wbl">məborak</item>
                <morphemes>
                  <morph type="stem" guid="d7f713e8-e8cf-11d3-9764-00c04f186933">
                    <item type="txt" lang="wbl">məborak</item>
                    <item type="cf" lang="wbl">muborak</item>
                    <item type="variantTypes" lang="en">+fr. var. of</item>
                    <item type="gls" lang="en">blessed</item>
                    <item type="msa" lang="en">adj</item>
                  </morph>
                </morphemes>
                <item type="gls" lang="en">blessed</item>
              </word>
              <word guid="55ec1a4b-6db7-4857-b675-23d8db645245">
                <item type="txt" lang="wbl">wuz</item>
                <morphemes>
                  <morph type="stem" guid="d7f713e8-e8cf-11d3-9764-00c04f186933">
                    <item type="txt" lang="wbl">wuz</item>
                    <item type="cf" lang="wbl">wuz</item>
                    <item type="gls" lang="en">1SG.NOM</item>
                    <item type="msa" lang="en">pronom</item>
                  </morph>
                </morphemes>
                <item type="gls" lang="en">1SG.NOM</item>
              </word>
              <word guid="3a13fb1f-80ef-4061-aed1-d6740e89b4ee">
                <item type="txt" lang="wbl">çanəm</item>
                <morphemes>
                  <morph type="stem" guid="d7f713e8-e8cf-11d3-9764-00c04f186933">
                    <item type="txt" lang="wbl">çan</item>
                    <item type="cf" lang="wbl">çan</item>
                    <item type="gls" lang="en">say</item>
                    <item type="msa" lang="en">v</item>
                  </morph>
                  <morph type="suffix" guid="d7f713dd-e8cf-11d3-9764-00c04f186933">
                    <item type="txt" lang="wbl">-əm</item>
                    <item type="cf" lang="wbl">-əm</item>
                    <item type="hn" lang="wbl">1</item>
                    <item type="gls" lang="en">-1SG.NPST</item>
                    <item type="msa" lang="en">v:Tns/Agr</item>
                  </morph>
                </morphemes>
                <item type="gls" lang="en"></item>
              </word>
              <word>
                <item type="punct" lang="en">.</item>
              </word>
            </words>
            <item type="gls" lang="en">It said, for you lovers, I wish a happy New Year.</item>
          </phrase>
        </phrases>
      </paragraph>
      <paragraph guid="dbf4dbd1-530f-4876-9a2c-58682cd329a3">
        <phrases>
          <phrase guid="72ad0e6a-c134-45cf-8e2f-ed52f9e13db2">
            <item type="segnum" lang="en">11</item>
            <words>
              <word guid="a6758e60-a77e-45d4-b478-e14cf3271fef">
                <item type="txt" lang="wbl">tatət</item>
                <morphemes>
                  <morph type="stem" guid="d7f713e8-e8cf-11d3-9764-00c04f186933">
                    <item type="txt" lang="wbl">tat</item>
                    <item type="cf" lang="wbl">tat</item>
                    <item type="gls" lang="en">father</item>
                    <item type="msa" lang="en">n</item>
                  </morph>
                  <morph type="enclitic" guid="d7f713e1-e8cf-11d3-9764-00c04f186933">
                    <item type="txt" lang="wbl">=ət</item>
                    <item type="cf" lang="wbl">=ət</item>
                    <item type="hn" lang="wbl">1</item>
                    <item type="gls" lang="en">=and</item>
                    <item type="msa" lang="en">conn</item>
                  </morph>
                </morphemes>
              </word>
              <word guid="d4c71934-29c1-416c-8a09-ac970af10455">
                <item type="txt" lang="wbl">nan</item>
                <morphemes>
                  <morph type="stem" guid="d7f713e8-e8cf-11d3-9764-00c04f186933">
                    <item type="txt" lang="wbl">nan</item>
                    <item type="cf" lang="wbl">nan</item>
                    <item type="gls" lang="en">mother</item>
                    <item type="msa" lang="en">n</item>
                  </morph>
                </morphemes>
                <item type="gls" lang="en">mother</item>
              </word>
              <word guid="ce85a84a-f1df-4bb5-a948-422058c232ad">
                <item type="txt" lang="wbl">çɨjət</item>
              </word>
              <word guid="f6e99d71-27df-45a7-974e-c12f0d0e880e">
                <item type="txt" lang="wbl">vrɨt</item>
                <morphemes>
                  <morph type="stem" guid="d7f713e8-e8cf-11d3-9764-00c04f186933">
                    <item type="txt" lang="wbl">vrɨt</item>
                    <item type="cf" lang="wbl">vrɨt</item>
                    <item type="hn" lang="wbl">1</item>
                    <item type="gls" lang="en">brother</item>
                    <item type="msa" lang="en">n</item>
                  </morph>
                </morphemes>
              </word>
              <word>
                <item type="punct" lang="en">,</item>
              </word>
              <word guid="7ca1d775-7472-4d01-aa3b-a7b73bab2308">
                <item type="txt" lang="wbl">mardi</item>
                <morphemes>
                  <morph type="stem" guid="d7f713e8-e8cf-11d3-9764-00c04f186933">
                    <item type="txt" lang="wbl">mard</item>
                    <item type="cf" lang="wbl">mard</item>
                    <item type="gls" lang="en">man</item>
                    <item type="msa" lang="en">n</item>
                  </morph>
                  <morph type="suffix" guid="d7f713dd-e8cf-11d3-9764-00c04f186933">
                    <item type="txt" lang="wbl">-i</item>
                    <item type="cf" lang="wbl">-i</item>
                    <item type="hn" lang="wbl">3</item>
                    <item type="gls" lang="en">-OBL</item>
                    <item type="msa" lang="en">n:(Case1)</item>
                  </morph>
                </morphemes>
                <item type="gls" lang="en">man</item>
              </word>
              <word guid="2fd240bc-9c6b-4cb4-972a-8ab2e42f2af2">
                <item type="txt" lang="wbl">diqonət</item>
              </word>
              <word guid="33a6df26-7ff5-4734-b29b-6cf92c075884">
                <item type="txt" lang="wbl">zmin</item>
                <morphemes>
                  <morph type="stem" guid="d7f713e8-e8cf-11d3-9764-00c04f186933">
                    <item type="txt" lang="wbl">zəmin</item>
                    <item type="cf" lang="wbl">zəmin</item>
                    <item type="gls" lang="en">earth</item>
                    <item type="msa" lang="en">n</item>
                  </morph>
                </morphemes>
                <item type="gls" lang="en">earth</item>
              </word>
              <word>
                <item type="punct" lang="en">.</item>
              </word>
            </words>
            <item type="gls" lang="en">Father, mother, sister and brother, gardener and the earth, </item>
          </phrase>
        </phrases>
      </paragraph>
      <paragraph guid="79e02601-01d3-4c0f-ba2f-7e8f29a0f053">
        <phrases>
          <phrase guid="b8a0dfd8-e629-4566-9b37-d2bbbf4e5624">
            <item type="segnum" lang="en">12</item>
            <words>
              <word guid="10032cfc-ae58-4b07-b0bb-098293b55db2">
                <item type="txt" lang="wbl">dilbari</item>
              </word>
              <word guid="5d97e205-d173-4f33-967d-19f7170dc526">
                <item type="txt" lang="wbl">mɨlki</item>
                <morphemes>
                  <morph type="stem" guid="d7f713e8-e8cf-11d3-9764-00c04f186933">
                    <item type="txt" lang="wbl">mɨlk</item>
                    <item type="cf" lang="wbl">mɨlk</item>
                    <item type="gls" lang="en">country</item>
                    <item type="msa" lang="en">n</item>
                  </morph>
                  <morph type="suffix" guid="d7f713dd-e8cf-11d3-9764-00c04f186933">
                    <item type="txt" lang="wbl">-i</item>
                    <item type="cf" lang="wbl">-i</item>
                    <item type="hn" lang="wbl">3</item>
                    <item type="gls" lang="en">-OBL</item>
                    <item type="msa" lang="en">n:(Case1)</item>
                  </morph>
                </morphemes>
              </word>
              <word guid="65bdfce5-c6cd-47e5-9dda-80489aaf94fa">
                <item type="txt" lang="wbl">waxon</item>
                <morphemes>
                  <morph type="stem" guid="d7f713e8-e8cf-11d3-9764-00c04f186933">
                    <item type="txt" lang="wbl">waxon</item>
                    <item type="cf" lang="wbl">waxon</item>
                    <item type="gls" lang="en">Wakhan</item>
                    <item type="msa" lang="en">n</item>
                  </morph>
                </morphemes>
                <item type="gls" lang="en">Wakhan</item>
              </word>
              <word>
                <item type="punct" lang="en">,</item>
              </word>
              <word guid="6efb877b-2e49-4208-bf7d-96ea5125c91f">
                <item type="txt" lang="wbl">ʃogɨn</item>
                <morphemes>
                  <morph type="stem" guid="d7f713e8-e8cf-11d3-9764-00c04f186933">
                    <item type="txt" lang="wbl">ʃogɨn</item>
                    <item type="cf" lang="wbl">ʃogɨn</item>
                    <item type="gls" lang="en">new.year</item>
                    <item type="msa" lang="en">n</item>
                  </morph>
                </morphemes>
                <item type="gls" lang="en">new.year</item>
              </word>
              <word guid="27582798-0d34-4731-b9ea-2b264146c356">
                <item type="txt" lang="wbl">məborak</item>
                <morphemes>
                  <morph type="stem" guid="d7f713e8-e8cf-11d3-9764-00c04f186933">
                    <item type="txt" lang="wbl">məborak</item>
                    <item type="cf" lang="wbl">muborak</item>
                    <item type="variantTypes" lang="en">+fr. var. of</item>
                    <item type="gls" lang="en">blessed</item>
                    <item type="msa" lang="en">adj</item>
                  </morph>
                </morphemes>
                <item type="gls" lang="en">blessed</item>
              </word>
              <word guid="55ec1a4b-6db7-4857-b675-23d8db645245">
                <item type="txt" lang="wbl">wuz</item>
                <morphemes>
                  <morph type="stem" guid="d7f713e8-e8cf-11d3-9764-00c04f186933">
                    <item type="txt" lang="wbl">wuz</item>
                    <item type="cf" lang="wbl">wuz</item>
                    <item type="gls" lang="en">1SG.NOM</item>
                    <item type="msa" lang="en">pronom</item>
                  </morph>
                </morphemes>
                <item type="gls" lang="en">1SG.NOM</item>
              </word>
              <word guid="3a13fb1f-80ef-4061-aed1-d6740e89b4ee">
                <item type="txt" lang="wbl">çanəm</item>
                <morphemes>
                  <morph type="stem" guid="d7f713e8-e8cf-11d3-9764-00c04f186933">
                    <item type="txt" lang="wbl">çan</item>
                    <item type="cf" lang="wbl">çan</item>
                    <item type="gls" lang="en">say</item>
                    <item type="msa" lang="en">v</item>
                  </morph>
                  <morph type="suffix" guid="d7f713dd-e8cf-11d3-9764-00c04f186933">
                    <item type="txt" lang="wbl">-əm</item>
                    <item type="cf" lang="wbl">-əm</item>
                    <item type="hn" lang="wbl">1</item>
                    <item type="gls" lang="en">-1SG.NPST</item>
                    <item type="msa" lang="en">v:Tns/Agr</item>
                  </morph>
                </morphemes>
                <item type="gls" lang="en"></item>
              </word>
              <word>
                <item type="punct" lang="en">.</item>
              </word>
            </words>
            <item type="gls" lang="en">Dilbar of the region of Wakhan, I wish you a happy New Year.</item>
          </phrase>
        </phrases>
      </paragraph>
      <paragraph guid="c96a851f-bac1-4c2d-bf02-90cb2eec4a12">
        <phrases>
          <phrase guid="e670c769-7851-4d27-b009-bc96250d5d3a">
            <item type="segnum" lang="en">13</item>
            <words>
              <word guid="b2e91bb6-ee9f-4e50-a936-468d1247ae82">
                <item type="txt" lang="wbl">kɨçtərət</item>
              </word>
              <word guid="0520f576-c206-47d3-aaa7-ef12e6fbf476">
                <item type="txt" lang="wbl">çati</item>
                <morphemes>
                  <morph type="stem" guid="d7f713e8-e8cf-11d3-9764-00c04f186933">
                    <item type="txt" lang="wbl">ça</item>
                    <item type="cf" lang="wbl">çan</item>
                    <item type="gls" lang="en">say</item>
                    <item type="msa" lang="en">v</item>
                  </morph>
                  <morph type="suffix" guid="d7f713dd-e8cf-11d3-9764-00c04f186933">
                    <item type="txt" lang="wbl">-t</item>
                    <item type="cf" lang="wbl">-t</item>
                    <item type="hn" lang="wbl">2</item>
                    <item type="gls" lang="en">-PST</item>
                    <item type="msa" lang="en">v:Pst1</item>
                  </morph>
                  <morph type="suffix" guid="d7f713dd-e8cf-11d3-9764-00c04f186933">
                    <item type="txt" lang="wbl">-i</item>
                    <item type="cf" lang="wbl">-i</item>
                    <item type="hn" lang="wbl">1</item>
                    <item type="gls" lang="en">-PST</item>
                    <item type="msa" lang="en">v:(Pst2)</item>
                  </morph>
                </morphemes>
                <item type="gls" lang="en"></item>
              </word>
              <word guid="27582798-0d34-4731-b9ea-2b264146c356">
                <item type="txt" lang="wbl">məborak</item>
                <morphemes>
                  <morph type="stem" guid="d7f713e8-e8cf-11d3-9764-00c04f186933">
                    <item type="txt" lang="wbl">məborak</item>
                    <item type="cf" lang="wbl">muborak</item>
                    <item type="variantTypes" lang="en">+fr. var. of</item>
                    <item type="gls" lang="en">blessed</item>
                    <item type="msa" lang="en">adj</item>
                  </morph>
                </morphemes>
                <item type="gls" lang="en">blessed</item>
              </word>
              <word guid="774035de-24b8-47a5-9f3e-f9623df874e1">
                <item type="txt" lang="wbl">sək</item>
                <morphemes>
                  <morph type="stem" guid="d7f713e8-e8cf-11d3-9764-00c04f186933">
                    <item type="txt" lang="wbl">sək</item>
                    <item type="cf" lang="wbl">sək</item>
                    <item type="gls" lang="en">in</item>
                    <item type="msa" lang="en">Loc/Dir</item>
                  </morph>
                </morphemes>
                <item type="gls" lang="en">in</item>
              </word>
              <word guid="3843a7e7-e993-4c75-87f7-fa15757f9af6">
                <item type="txt" lang="wbl">çik</item>
                <morphemes>
                  <morph type="stem" guid="d7f713e8-e8cf-11d3-9764-00c04f186933">
                    <item type="txt" lang="wbl">çik</item>
                    <item type="cf" lang="wbl">çik</item>
                    <item type="gls" lang="en">Wakhi</item>
                    <item type="msa" lang="en">n</item>
                  </morph>
                </morphemes>
                <item type="gls" lang="en">Wakhi</item>
              </word>
              <word guid="cb410360-b189-4da8-ab2a-5d266a5a87a9">
                <item type="txt" lang="wbl">zik</item>
                <morphemes>
                  <morph type="stem" guid="d7f713e8-e8cf-11d3-9764-00c04f186933">
                    <item type="txt" lang="wbl">zik</item>
                    <item type="cf" lang="wbl">zik</item>
                    <item type="gls" lang="en">tongue</item>
                    <item type="msa" lang="en">n</item>
                  </morph>
                </morphemes>
                <item type="gls" lang="en">language</item>
              </word>
              <word guid="03418ae5-65d4-43bb-afb1-adea8cc955d1">
                <item type="txt" lang="wbl">sanginmərod</item>
              </word>
              <word>
                <item type="punct" lang="en">.</item>
              </word>
            </words>
            <item type="gls" lang="fr">Sanginmurod, you told everyone congratulations in Wakhi,</item>
          </phrase>
        </phrases>
      </paragraph>
      <paragraph guid="6cc20cf2-20c9-4179-8b1a-aae6db0c1cf9">
        <phrases>
          <phrase guid="3769002c-c668-4af1-8bf5-33806f02e28f">
            <item type="segnum" lang="en">14</item>
            <words>
              <word guid="8579c532-11ad-4224-96a9-32bbfbb9728c">
                <item type="txt" lang="wbl">tar</item>
                <morphemes>
                  <morph type="stem" guid="d7f713e8-e8cf-11d3-9764-00c04f186933">
                    <item type="txt" lang="wbl">ta</item>
                    <item type="cf" lang="wbl">taw</item>
                    <item type="gls" lang="en">2SG.OBL</item>
                    <item type="msa" lang="en">pro-form</item>
                  </morph>
                  <morph type="suffix" guid="d7f713dd-e8cf-11d3-9764-00c04f186933">
                    <item type="txt" lang="wbl">-r</item>
                    <item type="cf" lang="wbl">-r</item>
                    <item type="gls" lang="en">-DAT</item>
                    <item type="msa" lang="en">n:(Case2)</item>
                  </morph>
                </morphemes>
                <item type="gls" lang="en"></item>
              </word>
              <word guid="2669cc3f-1502-4db7-89a6-355bb5b8ae6a">
                <item type="txt" lang="wbl">qəlam</item>
                <morphemes>
                  <morph type="stem" guid="d7f713e8-e8cf-11d3-9764-00c04f186933">
                    <item type="txt" lang="wbl">qəlam</item>
                    <item type="cf" lang="wbl">qəlam</item>
                    <item type="hn" lang="wbl">2</item>
                    <item type="gls" lang="en">pen</item>
                    <item type="msa" lang="en">n</item>
                  </morph>
                </morphemes>
                <item type="gls" lang="en">slice</item>
              </word>
              <word guid="05bbaae9-b9ab-42db-9697-6f1cf75ce489">
                <item type="txt" lang="wbl">çand</item>
                <morphemes>
                  <morph type="stem" guid="d7f713e8-e8cf-11d3-9764-00c04f186933">
                    <item type="txt" lang="wbl">çan</item>
                    <item type="cf" lang="wbl">çan</item>
                    <item type="gls" lang="en">say</item>
                    <item type="msa" lang="en">v</item>
                  </morph>
                  <morph type="suffix" guid="d7f713dd-e8cf-11d3-9764-00c04f186933">
                    <item type="txt" lang="wbl">-d</item>
                    <item type="cf" lang="wbl">-t</item>
                    <item type="hn" lang="wbl">1</item>
                    <item type="gls" lang="en">-3SG.NPST</item>
                    <item type="msa" lang="en">v:Tns/Agr</item>
                  </morph>
                </morphemes>
                <item type="gls" lang="en">says</item>
              </word>
              <word>
                <item type="punct" lang="en">,</item>
              </word>
              <word guid="38472ab6-c944-428e-9000-bf9c795a225c">
                <item type="txt" lang="wbl">aj</item>
                <morphemes>
                  <morph type="stem" guid="d7f713e8-e8cf-11d3-9764-00c04f186933">
                    <item type="txt" lang="wbl">aj</item>
                    <item type="cf" lang="wbl">aj</item>
                    <item type="hn" lang="wbl">1</item>
                    <item type="gls" lang="en">driving</item>
                    <item type="msa" lang="en">n</item>
                  </morph>
                </morphemes>
                <item type="gls" lang="en">push</item>
              </word>
              <word guid="0e51623d-b6a7-4f19-a4c7-4477188d7163">
                <item type="txt" lang="wbl">dʒəwon</item>
                <morphemes>
                  <morph type="stem" guid="d7f713e8-e8cf-11d3-9764-00c04f186933">
                    <item type="txt" lang="wbl">dʒəwon</item>
                    <item type="cf" lang="wbl">dʒuwon</item>
                    <item type="variantTypes" lang="en">+dial. var. of</item>
                    <item type="gls" lang="en">young</item>
                    <item type="msa" lang="en">adj</item>
                  </morph>
                </morphemes>
                <item type="gls" lang="en">young</item>
              </word>
              <word>
                <item type="punct" lang="en">,</item>
              </word>
              <word guid="6efb877b-2e49-4208-bf7d-96ea5125c91f">
                <item type="txt" lang="wbl">ʃogɨn</item>
                <morphemes>
                  <morph type="stem" guid="d7f713e8-e8cf-11d3-9764-00c04f186933">
                    <item type="txt" lang="wbl">ʃogɨn</item>
                    <item type="cf" lang="wbl">ʃogɨn</item>
                    <item type="gls" lang="en">new.year</item>
                    <item type="msa" lang="en">n</item>
                  </morph>
                </morphemes>
                <item type="gls" lang="en">new.year</item>
              </word>
              <word guid="27582798-0d34-4731-b9ea-2b264146c356">
                <item type="txt" lang="wbl">məborak</item>
                <morphemes>
                  <morph type="stem" guid="d7f713e8-e8cf-11d3-9764-00c04f186933">
                    <item type="txt" lang="wbl">məborak</item>
                    <item type="cf" lang="wbl">muborak</item>
                    <item type="variantTypes" lang="en">+fr. var. of</item>
                    <item type="gls" lang="en">blessed</item>
                    <item type="msa" lang="en">adj</item>
                  </morph>
                </morphemes>
                <item type="gls" lang="en">blessed</item>
              </word>
              <word guid="55ec1a4b-6db7-4857-b675-23d8db645245">
                <item type="txt" lang="wbl">wuz</item>
                <morphemes>
                  <morph type="stem" guid="d7f713e8-e8cf-11d3-9764-00c04f186933">
                    <item type="txt" lang="wbl">wuz</item>
                    <item type="cf" lang="wbl">wuz</item>
                    <item type="gls" lang="en">1SG.NOM</item>
                    <item type="msa" lang="en">pronom</item>
                  </morph>
                </morphemes>
                <item type="gls" lang="en">1SG.NOM</item>
              </word>
              <word guid="3a13fb1f-80ef-4061-aed1-d6740e89b4ee">
                <item type="txt" lang="wbl">çanəm</item>
                <morphemes>
                  <morph type="stem" guid="d7f713e8-e8cf-11d3-9764-00c04f186933">
                    <item type="txt" lang="wbl">çan</item>
                    <item type="cf" lang="wbl">çan</item>
                    <item type="gls" lang="en">say</item>
                    <item type="msa" lang="en">v</item>
                  </morph>
                  <morph type="suffix" guid="d7f713dd-e8cf-11d3-9764-00c04f186933">
                    <item type="txt" lang="wbl">-əm</item>
                    <item type="cf" lang="wbl">-əm</item>
                    <item type="hn" lang="wbl">1</item>
                    <item type="gls" lang="en">-1SG.NPST</item>
                    <item type="msa" lang="en">v:Tns/Agr</item>
                  </morph>
                </morphemes>
                <item type="gls" lang="en"></item>
              </word>
              <word>
                <item type="punct" lang="en">.</item>
              </word>
            </words>
            <item type="gls" lang="en">[But] for you a pencil says, hey young [man], I wish you a happy New Year. </item>
          </phrase>
        </phrases>
      </paragraph>
    </paragraphs>
    <languages>
      <language lang="en" font="Times New Roman" vernacular="true" />
      <language lang="wbl" font="Charis SIL" vernacular="true" />
      <language lang="wbl-Qaaa-TJ-x-Zipa" font="Charis SIL" />
      <language lang="fr" font="Times New Roman" />
    </languages>
  </interlinear-text>
  
</document>
